{
  "packageId": "ri_lw_ch_0582",
  "sourceRange": {
    "sourcePath": "D:\\workspace\\CodeBuddyWorkSpace\\RebornG_codebuddy\\doc\\original work\\reverend-insanity.txt",
    "chapterIds": [
      "ch_0582"
    ],
    "paragraphIds": [
      "ch_0582_p0002",
      "ch_0582_p0003",
      "ch_0582_p0005",
      "ch_0582_p0006",
      "ch_0582_p0008",
      "ch_0582_p0013",
      "ch_0582_p0016",
      "ch_0582_p0018",
      "ch_0582_p0025",
      "ch_0582_p0027",
      "ch_0582_p0029",
      "ch_0582_p0033",
      "ch_0582_p0034",
      "ch_0582_p0036",
      "ch_0582_p0043",
      "ch_0582_p0047",
      "ch_0582_p0051",
      "ch_0582_p0061",
      "ch_0582_p0062",
      "ch_0582_p0065",
      "ch_0582_p0066",
      "ch_0582_p0067",
      "ch_0582_p0068",
      "ch_0582_p0069",
      "ch_0582_p0072"
    ]
  },
  "entities": [
    {
      "sourcePointers": [
        {
          "sourcePath": "D:\\workspace\\CodeBuddyWorkSpace\\RebornG_codebuddy\\doc\\original work\\reverend-insanity.txt",
          "chapterId": "ch_0582",
          "paragraphId": "ch_0582_p0002",
          "startOffset": 2036825,
          "endOffset": 2036828,
          "summary": "马家族长，奴道蛊师"
        }
      ],
      "entityId": "entity_1ff9db2c17b2",
      "name": "马英杰",
      "kind": "person",
      "aliases": [
        "马族长"
      ],
      "description": "马家族长，奴道蛊师",
      "visibility": "ambiguous",
      "confidence": "medium"
    },
    {
      "sourcePointers": [
        {
          "sourcePath": "D:\\workspace\\CodeBuddyWorkSpace\\RebornG_codebuddy\\doc\\original work\\reverend-insanity.txt",
          "chapterId": "ch_0582",
          "paragraphId": "ch_0582_p0002",
          "startOffset": 2036829,
          "endOffset": 2036832,
          "summary": "马家族人，马英杰之子？"
        }
      ],
      "entityId": "entity_563b9539bf2e",
      "name": "马鸿运",
      "kind": "person",
      "aliases": [],
      "description": "马家族人，马英杰之子？",
      "visibility": "ambiguous",
      "confidence": "medium"
    },
    {
      "sourcePointers": [
        {
          "sourcePath": "D:\\workspace\\CodeBuddyWorkSpace\\RebornG_codebuddy\\doc\\original work\\reverend-insanity.txt",
          "chapterId": "ch_0582",
          "paragraphId": "ch_0582_p0003",
          "startOffset": 2036857,
          "endOffset": 2036859,
          "summary": "常家前族长，现任大长老"
        }
      ],
      "entityId": "entity_55634ca9557b",
      "name": "常飚",
      "kind": "person",
      "aliases": [
        "常兄"
      ],
      "description": "常家前族长，现任大长老",
      "visibility": "ambiguous",
      "confidence": "medium"
    },
    {
      "sourcePointers": [
        {
          "sourcePath": "D:\\workspace\\CodeBuddyWorkSpace\\RebornG_codebuddy\\doc\\original work\\reverend-insanity.txt",
          "chapterId": "ch_0582",
          "paragraphId": "ch_0582_p0003",
          "startOffset": 2036867,
          "endOffset": 2036869,
          "summary": "常家小姐"
        }
      ],
      "entityId": "entity_83602a79e257",
      "name": "常丽",
      "kind": "person",
      "aliases": [],
      "description": "常家小姐",
      "visibility": "ambiguous",
      "confidence": "medium"
    },
    {
      "sourcePointers": [
        {
          "sourcePath": "D:\\workspace\\CodeBuddyWorkSpace\\RebornG_codebuddy\\doc\\original work\\reverend-insanity.txt",
          "chapterId": "ch_0582",
          "paragraphId": "ch_0582_p0006",
          "startOffset": 2037027,
          "endOffset": 2037029,
          "summary": "黑家强者？"
        }
      ],
      "entityId": "entity_b865a7ec3956",
      "name": "潘平",
      "kind": "person",
      "aliases": [
        "潘兄"
      ],
      "description": "黑家强者？",
      "visibility": "ambiguous",
      "confidence": "medium"
    },
    {
      "sourcePointers": [
        {
          "sourcePath": "D:\\workspace\\CodeBuddyWorkSpace\\RebornG_codebuddy\\doc\\original work\\reverend-insanity.txt",
          "chapterId": "ch_0582",
          "paragraphId": "ch_0582_p0008",
          "startOffset": 2037081,
          "endOffset": 2037083,
          "summary": "马英杰的师傅，奴道蛊仙"
        }
      ],
      "entityId": "entity_6f444020b45b",
      "name": "马尊",
      "kind": "person",
      "aliases": [],
      "description": "马英杰的师傅，奴道蛊仙",
      "visibility": "ambiguous",
      "confidence": "medium"
    },
    {
      "sourcePointers": [
        {
          "sourcePath": "D:\\workspace\\CodeBuddyWorkSpace\\RebornG_codebuddy\\doc\\original work\\reverend-insanity.txt",
          "chapterId": "ch_0582",
          "paragraphId": "ch_0582_p0018",
          "startOffset": 2037543,
          "endOffset": 2037546,
          "summary": "常家现任族长，常飚义子"
        }
      ],
      "entityId": "entity_e7c53a4404a7",
      "name": "常极右",
      "kind": "person",
      "aliases": [],
      "description": "常家现任族长，常飚义子",
      "visibility": "ambiguous",
      "confidence": "medium"
    },
    {
      "sourcePointers": [
        {
          "sourcePath": "D:\\workspace\\CodeBuddyWorkSpace\\RebornG_codebuddy\\doc\\original work\\reverend-insanity.txt",
          "chapterId": "ch_0582",
          "paragraphId": "ch_0582_p0018",
          "startOffset": 2037555,
          "endOffset": 2037558,
          "summary": "常家真正主事者"
        }
      ],
      "entityId": "entity_72a780c6ee12",
      "name": "常山阴",
      "kind": "person",
      "aliases": [
        "狼王"
      ],
      "description": "常家真正主事者",
      "visibility": "ambiguous",
      "confidence": "medium"
    },
    {
      "sourcePointers": [
        {
          "sourcePath": "D:\\workspace\\CodeBuddyWorkSpace\\RebornG_codebuddy\\doc\\original work\\reverend-insanity.txt",
          "chapterId": "ch_0582",
          "paragraphId": "ch_0582_p0013",
          "startOffset": 2037281,
          "endOffset": 2037283,
          "summary": "兼修蛊师"
        }
      ],
      "entityId": "entity_9e7c4c6c397c",
      "name": "方源",
      "kind": "person",
      "aliases": [],
      "description": "兼修蛊师",
      "visibility": "ambiguous",
      "confidence": "medium"
    },
    {
      "sourcePointers": [
        {
          "sourcePath": "D:\\workspace\\CodeBuddyWorkSpace\\RebornG_codebuddy\\doc\\original work\\reverend-insanity.txt",
          "chapterId": "ch_0582",
          "paragraphId": "ch_0582_p0033",
          "startOffset": 2038352,
          "endOffset": 2038379,
          "summary": "马家成员，被任命为代理长老"
        }
      ],
      "entityId": "entity_563b9539bf2e",
      "name": "马鸿运",
      "kind": "person",
      "aliases": [],
      "description": "马家成员，被任命为代理长老",
      "visibility": "ambiguous",
      "confidence": "medium"
    },
    {
      "sourcePointers": [
        {
          "sourcePath": "D:\\workspace\\CodeBuddyWorkSpace\\RebornG_codebuddy\\doc\\original work\\reverend-insanity.txt",
          "chapterId": "ch_0582",
          "paragraphId": "ch_0582_p0034",
          "startOffset": 2038383,
          "endOffset": 2038439,
          "summary": "马家族长"
        }
      ],
      "entityId": "entity_1ff9db2c17b2",
      "name": "马英杰",
      "kind": "person",
      "aliases": [],
      "description": "马家族长",
      "visibility": "ambiguous",
      "confidence": "medium"
    },
    {
      "sourcePointers": [
        {
          "sourcePath": "D:\\workspace\\CodeBuddyWorkSpace\\RebornG_codebuddy\\doc\\original work\\reverend-insanity.txt",
          "chapterId": "ch_0582",
          "paragraphId": "ch_0582_p0036",
          "startOffset": 2038472,
          "endOffset": 2038571,
          "summary": "马鸿运的成亲对象"
        }
      ],
      "entityId": "entity_83602a79e257",
      "name": "常丽",
      "kind": "person",
      "aliases": [],
      "description": "马鸿运的成亲对象",
      "visibility": "ambiguous",
      "confidence": "medium"
    },
    {
      "sourcePointers": [
        {
          "sourcePath": "D:\\workspace\\CodeBuddyWorkSpace\\RebornG_codebuddy\\doc\\original work\\reverend-insanity.txt",
          "chapterId": "ch_0582",
          "paragraphId": "ch_0582_p0043",
          "startOffset": 2038786,
          "endOffset": 2038812,
          "summary": "炼蛊者，掌控八十八角真阳楼"
        }
      ],
      "entityId": "entity_9e7c4c6c397c",
      "name": "方源",
      "kind": "person",
      "aliases": [],
      "description": "炼蛊者，掌控八十八角真阳楼",
      "visibility": "ambiguous",
      "confidence": "medium"
    },
    {
      "sourcePointers": [
        {
          "sourcePath": "D:\\workspace\\CodeBuddyWorkSpace\\RebornG_codebuddy\\doc\\original work\\reverend-insanity.txt",
          "chapterId": "ch_0582",
          "paragraphId": "ch_0582_p0047",
          "startOffset": 2038917,
          "endOffset": 2039123,
          "summary": "方源脑海中的意志，传授炼道手法"
        }
      ],
      "entityId": "entity_f952f570efe5",
      "name": "墨瑶意志",
      "kind": "person",
      "aliases": [],
      "description": "方源脑海中的意志，传授炼道手法",
      "visibility": "ambiguous",
      "confidence": "medium"
    },
    {
      "sourcePointers": [
        {
          "sourcePath": "D:\\workspace\\CodeBuddyWorkSpace\\RebornG_codebuddy\\doc\\original work\\reverend-insanity.txt",
          "chapterId": "ch_0582",
          "paragraphId": "ch_0582_p0061",
          "startOffset": 2039534,
          "endOffset": 2039613,
          "summary": "打通八十八角真阳楼第七层的蛊师之一"
        }
      ],
      "entityId": "entity_55634ca9557b",
      "name": "常飚",
      "kind": "person",
      "aliases": [],
      "description": "打通八十八角真阳楼第七层的蛊师之一",
      "visibility": "ambiguous",
      "confidence": "medium"
    },
    {
      "sourcePointers": [
        {
          "sourcePath": "D:\\workspace\\CodeBuddyWorkSpace\\RebornG_codebuddy\\doc\\original work\\reverend-insanity.txt",
          "chapterId": "ch_0582",
          "paragraphId": "ch_0582_p0061",
          "startOffset": 2039534,
          "endOffset": 2039613,
          "summary": "打通八十八角真阳楼第七层的蛊师之一"
        }
      ],
      "entityId": "entity_b865a7ec3956",
      "name": "潘平",
      "kind": "person",
      "aliases": [],
      "description": "打通八十八角真阳楼第七层的蛊师之一",
      "visibility": "ambiguous",
      "confidence": "medium"
    },
    {
      "sourcePointers": [
        {
          "sourcePath": "D:\\workspace\\CodeBuddyWorkSpace\\RebornG_codebuddy\\doc\\original work\\reverend-insanity.txt",
          "chapterId": "ch_0582",
          "paragraphId": "ch_0582_p0066",
          "startOffset": 2039828,
          "endOffset": 2039830,
          "summary": "五转蛊师，代理家老"
        }
      ],
      "entityId": "entity_9e7c4c6c397c",
      "name": "方源",
      "kind": "person",
      "aliases": [],
      "description": "五转蛊师，代理家老",
      "visibility": "ambiguous",
      "confidence": "medium"
    },
    {
      "sourcePointers": [
        {
          "sourcePath": "D:\\workspace\\CodeBuddyWorkSpace\\RebornG_codebuddy\\doc\\original work\\reverend-insanity.txt",
          "chapterId": "ch_0582",
          "paragraphId": "ch_0582_p0066",
          "startOffset": 2039856,
          "endOffset": 2039861,
          "summary": "意志体，存在于方源脑海"
        }
      ],
      "entityId": "entity_f952f570efe5",
      "name": "墨瑶意志",
      "kind": "person",
      "aliases": [],
      "description": "意志体，存在于方源脑海",
      "visibility": "ambiguous",
      "confidence": "medium"
    },
    {
      "sourcePointers": [
        {
          "sourcePath": "D:\\workspace\\CodeBuddyWorkSpace\\RebornG_codebuddy\\doc\\original work\\reverend-insanity.txt",
          "chapterId": "ch_0582",
          "paragraphId": "ch_0582_p0069",
          "startOffset": 2039965,
          "endOffset": 2039967,
          "summary": "蛊师，在五转楼主第七层闯关"
        }
      ],
      "entityId": "entity_55634ca9557b",
      "name": "常飚",
      "kind": "person",
      "aliases": [],
      "description": "蛊师，在五转楼主第七层闯关",
      "visibility": "ambiguous",
      "confidence": "medium"
    },
    {
      "sourcePointers": [
        {
          "sourcePath": "D:\\workspace\\CodeBuddyWorkSpace\\RebornG_codebuddy\\doc\\original work\\reverend-insanity.txt",
          "chapterId": "ch_0582",
          "paragraphId": "ch_0582_p0069",
          "startOffset": 2039970,
          "endOffset": 2039972,
          "summary": "蛊师，在五转楼主第七层闯关"
        }
      ],
      "entityId": "entity_b865a7ec3956",
      "name": "潘平",
      "kind": "person",
      "aliases": [],
      "description": "蛊师，在五转楼主第七层闯关",
      "visibility": "ambiguous",
      "confidence": "medium"
    }
  ],
  "relations": [
    {
      "sourcePointers": [
        {
          "sourcePath": "D:\\workspace\\CodeBuddyWorkSpace\\RebornG_codebuddy\\doc\\original work\\reverend-insanity.txt",
          "chapterId": "ch_0582",
          "paragraphId": "ch_0582_p0025",
          "startOffset": 2037908,
          "endOffset": 2037938,
          "summary": "马英杰与常飚结盟，以兄弟相称，并约定联姻"
        }
      ],
      "relationId": "rel_c52e4665f0ff",
      "subject": "马英杰",
      "object": "常飚",
      "relationType": "ALLY",
      "summary": "马英杰与常飚结盟，以兄弟相称，并约定联姻",
      "timeRange": "",
      "visibility": "ambiguous",
      "confidence": "medium"
    },
    {
      "sourcePointers": [
        {
          "sourcePath": "D:\\workspace\\CodeBuddyWorkSpace\\RebornG_codebuddy\\doc\\original work\\reverend-insanity.txt",
          "chapterId": "ch_0582",
          "paragraphId": "ch_0582_p0025",
          "startOffset": 2037908,
          "endOffset": 2037938,
          "summary": "马英杰与潘平结盟，以兄弟相称"
        }
      ],
      "relationId": "rel_b26591e61894",
      "subject": "马英杰",
      "object": "潘平",
      "relationType": "ALLY",
      "summary": "马英杰与潘平结盟，以兄弟相称",
      "timeRange": "",
      "visibility": "ambiguous",
      "confidence": "medium"
    },
    {
      "sourcePointers": [
        {
          "sourcePath": "D:\\workspace\\CodeBuddyWorkSpace\\RebornG_codebuddy\\doc\\original work\\reverend-insanity.txt",
          "chapterId": "ch_0582",
          "paragraphId": "ch_0582_p0027",
          "startOffset": 2038012,
          "endOffset": 2038020,
          "summary": "马鸿运与常丽定下婚约"
        }
      ],
      "relationId": "rel_4c3e85b03a47",
      "subject": "马鸿运",
      "object": "常丽",
      "relationType": "FAMILY",
      "summary": "马鸿运与常丽定下婚约",
      "timeRange": "",
      "visibility": "ambiguous",
      "confidence": "medium"
    },
    {
      "sourcePointers": [
        {
          "sourcePath": "D:\\workspace\\CodeBuddyWorkSpace\\RebornG_codebuddy\\doc\\original work\\reverend-insanity.txt",
          "chapterId": "ch_0582",
          "paragraphId": "ch_0582_p0029",
          "startOffset": 2038087,
          "endOffset": 2038147,
          "summary": "常飚对常山阴有异心，意图联合马英杰对抗常山阴"
        }
      ],
      "relationId": "rel_a5e5daee9215",
      "subject": "常飚",
      "object": "常山阴",
      "relationType": "CONFLICT",
      "summary": "常飚对常山阴有异心，意图联合马英杰对抗常山阴",
      "timeRange": "",
      "visibility": "ambiguous",
      "confidence": "medium"
    },
    {
      "sourcePointers": [
        {
          "sourcePath": "D:\\workspace\\CodeBuddyWorkSpace\\RebornG_codebuddy\\doc\\original work\\reverend-insanity.txt",
          "chapterId": "ch_0582",
          "paragraphId": "ch_0582_p0008",
          "startOffset": 2037059,
          "endOffset": 2037089,
          "summary": "马尊是马英杰的师傅，传授奴道传承"
        }
      ],
      "relationId": "rel_1e7d4386a5a5",
      "subject": "马英杰",
      "object": "马尊",
      "relationType": "MENTOR",
      "summary": "马尊是马英杰的师傅，传授奴道传承",
      "timeRange": "",
      "visibility": "ambiguous",
      "confidence": "medium"
    },
    {
      "sourcePointers": [
        {
          "sourcePath": "D:\\workspace\\CodeBuddyWorkSpace\\RebornG_codebuddy\\doc\\original work\\reverend-insanity.txt",
          "chapterId": "ch_0582",
          "paragraphId": "ch_0582_p0036",
          "startOffset": 2038472,
          "endOffset": 2038571,
          "summary": "马英杰任命马鸿运为代理长老，并赐予赤铁舍利蛊，鼓励其与常丽成亲"
        }
      ],
      "relationId": "rel_86cecdefa2f0",
      "subject": "马英杰",
      "object": "马鸿运",
      "relationType": "FAMILY",
      "summary": "马英杰任命马鸿运为代理长老，并赐予赤铁舍利蛊，鼓励其与常丽成亲",
      "timeRange": "",
      "visibility": "ambiguous",
      "confidence": "medium"
    },
    {
      "sourcePointers": [
        {
          "sourcePath": "D:\\workspace\\CodeBuddyWorkSpace\\RebornG_codebuddy\\doc\\original work\\reverend-insanity.txt",
          "chapterId": "ch_0582",
          "paragraphId": "ch_0582_p0047",
          "startOffset": 2038917,
          "endOffset": 2039123,
          "summary": "墨瑶意志传授方源炼道手法骤雨"
        }
      ],
      "relationId": "rel_3bfdd9cfcc43",
      "subject": "方源",
      "object": "墨瑶意志",
      "relationType": "MENTOR",
      "summary": "墨瑶意志传授方源炼道手法骤雨",
      "timeRange": "",
      "visibility": "ambiguous",
      "confidence": "medium"
    },
    {
      "sourcePointers": [
        {
          "sourcePath": "D:\\workspace\\CodeBuddyWorkSpace\\RebornG_codebuddy\\doc\\original work\\reverend-insanity.txt",
          "chapterId": "ch_0582",
          "paragraphId": "ch_0582_p0061",
          "startOffset": 2039534,
          "endOffset": 2039613,
          "summary": "方源利用楼主令暗扣常飚等人通关奖励的仙元石，并给予削减版杀招"
        }
      ],
      "relationId": "rel_1478c9307161",
      "subject": "方源",
      "object": "常飚",
      "relationType": "CONFLICT",
      "summary": "方源利用楼主令暗扣常飚等人通关奖励的仙元石，并给予削减版杀招",
      "timeRange": "",
      "visibility": "ambiguous",
      "confidence": "medium"
    },
    {
      "sourcePointers": [
        {
          "sourcePath": "D:\\workspace\\CodeBuddyWorkSpace\\RebornG_codebuddy\\doc\\original work\\reverend-insanity.txt",
          "chapterId": "ch_0582",
          "paragraphId": "ch_0582_p0061",
          "startOffset": 2039534,
          "endOffset": 2039613,
          "summary": "方源利用楼主令暗扣潘平等人通关奖励的仙元石，并给予削减版杀招"
        }
      ],
      "relationId": "rel_c789511ef259",
      "subject": "方源",
      "object": "潘平",
      "relationType": "CONFLICT",
      "summary": "方源利用楼主令暗扣潘平等人通关奖励的仙元石，并给予削减版杀招",
      "timeRange": "",
      "visibility": "ambiguous",
      "confidence": "medium"
    },
    {
      "sourcePointers": [
        {
          "sourcePath": "D:\\workspace\\CodeBuddyWorkSpace\\RebornG_codebuddy\\doc\\original work\\reverend-insanity.txt",
          "chapterId": "ch_0582",
          "paragraphId": "ch_0582_p0061",
          "startOffset": 2039534,
          "endOffset": 2039613,
          "summary": "方源利用楼主令暗扣马英杰等人通关奖励的仙元石，并给予削减版杀招"
        }
      ],
      "relationId": "rel_8f44df193324",
      "subject": "方源",
      "object": "马英杰",
      "relationType": "CONFLICT",
      "summary": "方源利用楼主令暗扣马英杰等人通关奖励的仙元石，并给予削减版杀招",
      "timeRange": "",
      "visibility": "ambiguous",
      "confidence": "medium"
    },
    {
      "sourcePointers": [
        {
          "sourcePath": "D:\\workspace\\CodeBuddyWorkSpace\\RebornG_codebuddy\\doc\\original work\\reverend-insanity.txt",
          "chapterId": "ch_0582",
          "paragraphId": "ch_0582_p0066",
          "startOffset": 2039828,
          "endOffset": 2039861,
          "summary": "方源与脑海中的墨瑶意志商议杀招奖励事宜"
        }
      ],
      "relationId": "rel_2f55c3537705",
      "subject": "方源",
      "object": "墨瑶意志",
      "relationType": "OTHER",
      "summary": "方源与脑海中的墨瑶意志商议杀招奖励事宜",
      "timeRange": "",
      "visibility": "ambiguous",
      "confidence": "medium"
    },
    {
      "sourcePointers": [
        {
          "sourcePath": "D:\\workspace\\CodeBuddyWorkSpace\\RebornG_codebuddy\\doc\\original work\\reverend-insanity.txt",
          "chapterId": "ch_0582",
          "paragraphId": "ch_0582_p0069",
          "startOffset": 2039965,
          "endOffset": 2039972,
          "summary": "常飚和潘平一同在五转楼主第七层闯关"
        }
      ],
      "relationId": "rel_e6ddda35427b",
      "subject": "常飚",
      "object": "潘平",
      "relationType": "ALLY",
      "summary": "常飚和潘平一同在五转楼主第七层闯关",
      "timeRange": "",
      "visibility": "ambiguous",
      "confidence": "medium"
    }
  ],
  "events": [
    {
      "sourcePointers": [
        {
          "sourcePath": "D:\\workspace\\CodeBuddyWorkSpace\\RebornG_codebuddy\\doc\\original work\\reverend-insanity.txt",
          "chapterId": "ch_0582",
          "paragraphId": "ch_0582_p0002",
          "startOffset": 2036825,
          "endOffset": 2036845,
          "summary": "马英杰带马鸿运前往常家赴宴"
        }
      ],
      "eventId": "evt_824a2cc88ce8",
      "eventType": "other",
      "summary": "马英杰带马鸿运前往常家赴宴",
      "actors": [
        "马英杰",
        "马鸿运"
      ],
      "affectedEntities": [],
      "causes": [],
      "consequences": [
        "为后续联姻和结盟铺垫"
      ],
      "knownObservers": [],
      "hiddenObservers": [],
      "visibility": "ambiguous",
      "confidence": "medium"
    },
    {
      "sourcePointers": [
        {
          "sourcePath": "D:\\workspace\\CodeBuddyWorkSpace\\RebornG_codebuddy\\doc\\original work\\reverend-insanity.txt",
          "chapterId": "ch_0582",
          "paragraphId": "ch_0582_p0003",
          "startOffset": 2036849,
          "endOffset": 2036879,
          "summary": "常飚挽留马鸿运密谈，并让常丽款待"
        }
      ],
      "eventId": "evt_203a16961434",
      "eventType": "other",
      "summary": "常飚挽留马鸿运密谈，并让常丽款待",
      "actors": [
        "常飚",
        "马鸿运",
        "常丽"
      ],
      "affectedEntities": [],
      "causes": [],
      "consequences": [
        "促成马鸿运与常丽的婚约"
      ],
      "knownObservers": [],
      "hiddenObservers": [],
      "visibility": "ambiguous",
      "confidence": "medium"
    },
    {
      "sourcePointers": [
        {
          "sourcePath": "D:\\workspace\\CodeBuddyWorkSpace\\RebornG_codebuddy\\doc\\original work\\reverend-insanity.txt",
          "chapterId": "ch_0582",
          "paragraphId": "ch_0582_p0005",
          "startOffset": 2036938,
          "endOffset": 2036978,
          "summary": "马英杰表示要贩卖六臂天尸王杀招，常飚和潘平请求保密"
        }
      ],
      "eventId": "evt_6c4ad48448bc",
      "eventType": "trade",
      "summary": "马英杰表示要贩卖六臂天尸王杀招，常飚和潘平请求保密",
      "actors": [
        "马英杰",
        "常飚",
        "潘平"
      ],
      "affectedEntities": [],
      "causes": [],
      "consequences": [
        "三人达成保密协议"
      ],
      "knownObservers": [],
      "hiddenObservers": [],
      "visibility": "ambiguous",
      "confidence": "medium"
    },
    {
      "sourcePointers": [
        {
          "sourcePath": "D:\\workspace\\CodeBuddyWorkSpace\\RebornG_codebuddy\\doc\\original work\\reverend-insanity.txt",
          "chapterId": "ch_0582",
          "paragraphId": "ch_0582_p0027",
          "startOffset": 2037996,
          "endOffset": 2038020,
          "summary": "三人密谈至深夜，定下马鸿运与常丽的婚约"
        }
      ],
      "eventId": "evt_36994f60f5c6",
      "eventType": "other",
      "summary": "三人密谈至深夜，定下马鸿运与常丽的婚约",
      "actors": [
        "马英杰",
        "常飚",
        "潘平"
      ],
      "affectedEntities": [],
      "causes": [],
      "consequences": [
        "马家与常家联姻"
      ],
      "knownObservers": [],
      "hiddenObservers": [],
      "visibility": "ambiguous",
      "confidence": "medium"
    },
    {
      "sourcePointers": [
        {
          "sourcePath": "D:\\workspace\\CodeBuddyWorkSpace\\RebornG_codebuddy\\doc\\original work\\reverend-insanity.txt",
          "chapterId": "ch_0582",
          "paragraphId": "ch_0582_p0036",
          "startOffset": 2038472,
          "endOffset": 2038571,
          "summary": "马英杰任命马鸿运为代理长老，并赐予三只赤铁舍利蛊"
        }
      ],
      "eventId": "evt_a3014f8f1883",
      "eventType": "other",
      "summary": "马英杰任命马鸿运为代理长老，并赐予三只赤铁舍利蛊",
      "actors": [
        "马英杰",
        "马鸿运"
      ],
      "affectedEntities": [],
      "causes": [],
      "consequences": [
        "马鸿运成为代理长老，实力有望提升至二转巅峰"
      ],
      "knownObservers": [],
      "hiddenObservers": [],
      "visibility": "ambiguous",
      "confidence": "medium"
    },
    {
      "sourcePointers": [
        {
          "sourcePath": "D:\\workspace\\CodeBuddyWorkSpace\\RebornG_codebuddy\\doc\\original work\\reverend-insanity.txt",
          "chapterId": "ch_0582",
          "paragraphId": "ch_0582_p0051",
          "startOffset": 2039232,
          "endOffset": 2039255,
          "summary": "方源使用炼道手法骤雨，对楼主令进行第五次墨化"
        }
      ],
      "eventId": "evt_66785ab154e3",
      "eventType": "cultivation",
      "summary": "方源使用炼道手法骤雨，对楼主令进行第五次墨化",
      "actors": [
        "方源"
      ],
      "affectedEntities": [],
      "causes": [],
      "consequences": [
        "楼主令具备五个角，方源掌控第七层并暗扣五颗仙元石"
      ],
      "knownObservers": [],
      "hiddenObservers": [],
      "visibility": "ambiguous",
      "confidence": "medium"
    },
    {
      "sourcePointers": [
        {
          "sourcePath": "D:\\workspace\\CodeBuddyWorkSpace\\RebornG_codebuddy\\doc\\original work\\reverend-insanity.txt",
          "chapterId": "ch_0582",
          "paragraphId": "ch_0582_p0061",
          "startOffset": 2039534,
          "endOffset": 2039613,
          "summary": "方源利用楼主令掌控第七层，暗扣常飚、潘平、马英杰等人通关奖励的五颗仙元石，并给予削减版的六臂天尸王杀招"
        }
      ],
      "eventId": "evt_435da1121528",
      "eventType": "trade",
      "summary": "方源利用楼主令掌控第七层，暗扣常飚、潘平、马英杰等人通关奖励的五颗仙元石，并给予削减版的六臂天尸王杀招",
      "actors": [
        "方源",
        "常飚",
        "潘平",
        "马英杰"
      ],
      "affectedEntities": [],
      "causes": [],
      "consequences": [
        "方源获得五颗仙元石，常飚等人得到削弱版杀招"
      ],
      "knownObservers": [],
      "hiddenObservers": [],
      "visibility": "ambiguous",
      "confidence": "medium"
    },
    {
      "sourcePointers": [
        {
          "sourcePath": "D:\\workspace\\CodeBuddyWorkSpace\\RebornG_codebuddy\\doc\\original work\\reverend-insanity.txt",
          "chapterId": "ch_0582",
          "paragraphId": "ch_0582_p0067",
          "startOffset": 2039891,
          "endOffset": 2039920,
          "summary": "方源与墨瑶意志商议，决定先取走两套杀招奖励，观察结果"
        }
      ],
      "eventId": "evt_ac93f62d1984",
      "eventType": "other",
      "summary": "方源与墨瑶意志商议，决定先取走两套杀招奖励，观察结果",
      "actors": [
        "方源",
        "墨瑶意志"
      ],
      "affectedEntities": [],
      "causes": [],
      "consequences": [
        "方源准备通过五角楼主令操控第七层关卡"
      ],
      "knownObservers": [],
      "hiddenObservers": [],
      "visibility": "ambiguous",
      "confidence": "medium"
    },
    {
      "sourcePointers": [
        {
          "sourcePath": "D:\\workspace\\CodeBuddyWorkSpace\\RebornG_codebuddy\\doc\\original work\\reverend-insanity.txt",
          "chapterId": "ch_0582",
          "paragraphId": "ch_0582_p0068",
          "startOffset": 2039924,
          "endOffset": 2039961,
          "summary": "方源握住五角楼主令，发现第七层第九十关卡中有常飚和潘平"
        }
      ],
      "eventId": "evt_47c3f221d878",
      "eventType": "other",
      "summary": "方源握住五角楼主令，发现第七层第九十关卡中有常飚和潘平",
      "actors": [
        "方源"
      ],
      "affectedEntities": [],
      "causes": [],
      "consequences": [
        "方源掌控第七层，发现两人后，一切将不同"
      ],
      "knownObservers": [],
      "hiddenObservers": [],
      "visibility": "ambiguous",
      "confidence": "medium"
    }
  ],
  "timeline": [
    {
      "sourcePointers": [
        {
          "sourcePath": "D:\\workspace\\CodeBuddyWorkSpace\\RebornG_codebuddy\\doc\\original work\\reverend-insanity.txt",
          "chapterId": "ch_0582",
          "paragraphId": "ch_0582_p0002",
          "startOffset": 2036825,
          "endOffset": 2036845,
          "summary": "马英杰带马鸿运前往常家赴宴"
        }
      ],
      "timelineId": "tl_824a2cc88ce8",
      "eventId": "evt_824a2cc88ce8",
      "chapterId": "ch_0582",
      "orderHint": "chapter-order",
      "summary": "马英杰带马鸿运前往常家赴宴",
      "confidence": "medium"
    },
    {
      "sourcePointers": [
        {
          "sourcePath": "D:\\workspace\\CodeBuddyWorkSpace\\RebornG_codebuddy\\doc\\original work\\reverend-insanity.txt",
          "chapterId": "ch_0582",
          "paragraphId": "ch_0582_p0003",
          "startOffset": 2036849,
          "endOffset": 2036879,
          "summary": "常飚挽留马鸿运密谈，并让常丽款待"
        }
      ],
      "timelineId": "tl_203a16961434",
      "eventId": "evt_203a16961434",
      "chapterId": "ch_0582",
      "orderHint": "chapter-order",
      "summary": "常飚挽留马鸿运密谈，并让常丽款待",
      "confidence": "medium"
    },
    {
      "sourcePointers": [
        {
          "sourcePath": "D:\\workspace\\CodeBuddyWorkSpace\\RebornG_codebuddy\\doc\\original work\\reverend-insanity.txt",
          "chapterId": "ch_0582",
          "paragraphId": "ch_0582_p0005",
          "startOffset": 2036938,
          "endOffset": 2036978,
          "summary": "马英杰表示要贩卖六臂天尸王杀招，常飚和潘平请求保密"
        }
      ],
      "timelineId": "tl_6c4ad48448bc",
      "eventId": "evt_6c4ad48448bc",
      "chapterId": "ch_0582",
      "orderHint": "chapter-order",
      "summary": "马英杰表示要贩卖六臂天尸王杀招，常飚和潘平请求保密",
      "confidence": "medium"
    },
    {
      "sourcePointers": [
        {
          "sourcePath": "D:\\workspace\\CodeBuddyWorkSpace\\RebornG_codebuddy\\doc\\original work\\reverend-insanity.txt",
          "chapterId": "ch_0582",
          "paragraphId": "ch_0582_p0027",
          "startOffset": 2037996,
          "endOffset": 2038020,
          "summary": "三人密谈至深夜，定下马鸿运与常丽的婚约"
        }
      ],
      "timelineId": "tl_36994f60f5c6",
      "eventId": "evt_36994f60f5c6",
      "chapterId": "ch_0582",
      "orderHint": "chapter-order",
      "summary": "三人密谈至深夜，定下马鸿运与常丽的婚约",
      "confidence": "medium"
    },
    {
      "sourcePointers": [
        {
          "sourcePath": "D:\\workspace\\CodeBuddyWorkSpace\\RebornG_codebuddy\\doc\\original work\\reverend-insanity.txt",
          "chapterId": "ch_0582",
          "paragraphId": "ch_0582_p0036",
          "startOffset": 2038472,
          "endOffset": 2038571,
          "summary": "马英杰任命马鸿运为代理长老，并赐予三只赤铁舍利蛊"
        }
      ],
      "timelineId": "tl_a3014f8f1883",
      "eventId": "evt_a3014f8f1883",
      "chapterId": "ch_0582",
      "orderHint": "chapter-order",
      "summary": "马英杰任命马鸿运为代理长老，并赐予三只赤铁舍利蛊",
      "confidence": "medium"
    },
    {
      "sourcePointers": [
        {
          "sourcePath": "D:\\workspace\\CodeBuddyWorkSpace\\RebornG_codebuddy\\doc\\original work\\reverend-insanity.txt",
          "chapterId": "ch_0582",
          "paragraphId": "ch_0582_p0051",
          "startOffset": 2039232,
          "endOffset": 2039255,
          "summary": "方源使用炼道手法骤雨，对楼主令进行第五次墨化"
        }
      ],
      "timelineId": "tl_66785ab154e3",
      "eventId": "evt_66785ab154e3",
      "chapterId": "ch_0582",
      "orderHint": "chapter-order",
      "summary": "方源使用炼道手法骤雨，对楼主令进行第五次墨化",
      "confidence": "medium"
    },
    {
      "sourcePointers": [
        {
          "sourcePath": "D:\\workspace\\CodeBuddyWorkSpace\\RebornG_codebuddy\\doc\\original work\\reverend-insanity.txt",
          "chapterId": "ch_0582",
          "paragraphId": "ch_0582_p0061",
          "startOffset": 2039534,
          "endOffset": 2039613,
          "summary": "方源利用楼主令掌控第七层，暗扣常飚、潘平、马英杰等人通关奖励的五颗仙元石，并给予削减版的六臂天尸王杀招"
        }
      ],
      "timelineId": "tl_435da1121528",
      "eventId": "evt_435da1121528",
      "chapterId": "ch_0582",
      "orderHint": "chapter-order",
      "summary": "方源利用楼主令掌控第七层，暗扣常飚、潘平、马英杰等人通关奖励的五颗仙元石，并给予削减版的六臂天尸王杀招",
      "confidence": "medium"
    },
    {
      "sourcePointers": [
        {
          "sourcePath": "D:\\workspace\\CodeBuddyWorkSpace\\RebornG_codebuddy\\doc\\original work\\reverend-insanity.txt",
          "chapterId": "ch_0582",
          "paragraphId": "ch_0582_p0067",
          "startOffset": 2039891,
          "endOffset": 2039920,
          "summary": "方源与墨瑶意志商议，决定先取走两套杀招奖励，观察结果"
        }
      ],
      "timelineId": "tl_ac93f62d1984",
      "eventId": "evt_ac93f62d1984",
      "chapterId": "ch_0582",
      "orderHint": "chapter-order",
      "summary": "方源与墨瑶意志商议，决定先取走两套杀招奖励，观察结果",
      "confidence": "medium"
    },
    {
      "sourcePointers": [
        {
          "sourcePath": "D:\\workspace\\CodeBuddyWorkSpace\\RebornG_codebuddy\\doc\\original work\\reverend-insanity.txt",
          "chapterId": "ch_0582",
          "paragraphId": "ch_0582_p0068",
          "startOffset": 2039924,
          "endOffset": 2039961,
          "summary": "方源握住五角楼主令，发现第七层第九十关卡中有常飚和潘平"
        }
      ],
      "timelineId": "tl_47c3f221d878",
      "eventId": "evt_47c3f221d878",
      "chapterId": "ch_0582",
      "orderHint": "chapter-order",
      "summary": "方源握住五角楼主令，发现第七层第九十关卡中有常飚和潘平",
      "confidence": "medium"
    }
  ],
  "hiddenFacts": [],
  "characterMotives": [],
  "factionPressures": [
    {
      "sourcePointers": [
        {
          "sourcePath": "D:\\workspace\\CodeBuddyWorkSpace\\RebornG_codebuddy\\doc\\original work\\reverend-insanity.txt",
          "chapterId": "ch_0582",
          "paragraphId": "ch_0582_p0002",
          "startOffset": 2036825,
          "endOffset": 2036828,
          "summary": "马家族长，奴道蛊师"
        },
        {
          "sourcePath": "D:\\workspace\\CodeBuddyWorkSpace\\RebornG_codebuddy\\doc\\original work\\reverend-insanity.txt",
          "chapterId": "ch_0582",
          "paragraphId": "ch_0582_p0002",
          "startOffset": 2036829,
          "endOffset": 2036832,
          "summary": "马家族人，马英杰之子？"
        },
        {
          "sourcePath": "D:\\workspace\\CodeBuddyWorkSpace\\RebornG_codebuddy\\doc\\original work\\reverend-insanity.txt",
          "chapterId": "ch_0582",
          "paragraphId": "ch_0582_p0033",
          "startOffset": 2038352,
          "endOffset": 2038379,
          "summary": "马家成员，被任命为代理长老"
        },
        {
          "sourcePath": "D:\\workspace\\CodeBuddyWorkSpace\\RebornG_codebuddy\\doc\\original work\\reverend-insanity.txt",
          "chapterId": "ch_0582",
          "paragraphId": "ch_0582_p0034",
          "startOffset": 2038383,
          "endOffset": 2038439,
          "summary": "马家族长"
        },
        {
          "sourcePath": "D:\\workspace\\CodeBuddyWorkSpace\\RebornG_codebuddy\\doc\\original work\\reverend-insanity.txt",
          "chapterId": "ch_0582",
          "paragraphId": "ch_0582_p0036",
          "startOffset": 2038472,
          "endOffset": 2038571,
          "summary": "马鸿运的成亲对象"
        }
      ],
      "pressureId": "pressure_1",
      "faction": "马家",
      "pressureAxis": "联姻与内部权力交接",
      "beneficiaries": [],
      "victims": [],
      "likelyReactions": [
        "观察马鸿运与常丽联姻进展",
        "巩固内部权力"
      ],
      "confidence": "medium"
    },
    {
      "sourcePointers": [
        {
          "sourcePath": "D:\\workspace\\CodeBuddyWorkSpace\\RebornG_codebuddy\\doc\\original work\\reverend-insanity.txt",
          "chapterId": "ch_0582",
          "paragraphId": "ch_0582_p0003",
          "startOffset": 2036857,
          "endOffset": 2036859,
          "summary": "常家前族长，现任大长老"
        },
        {
          "sourcePath": "D:\\workspace\\CodeBuddyWorkSpace\\RebornG_codebuddy\\doc\\original work\\reverend-insanity.txt",
          "chapterId": "ch_0582",
          "paragraphId": "ch_0582_p0018",
          "startOffset": 2037543,
          "endOffset": 2037546,
          "summary": "常家现任族长，常飚义子"
        },
        {
          "sourcePath": "D:\\workspace\\CodeBuddyWorkSpace\\RebornG_codebuddy\\doc\\original work\\reverend-insanity.txt",
          "chapterId": "ch_0582",
          "paragraphId": "ch_0582_p0018",
          "startOffset": 2037555,
          "endOffset": 2037558,
          "summary": "常家真正主事者"
        }
      ],
      "pressureId": "pressure_2",
      "faction": "常家",
      "pressureAxis": "内部权力斗争与外部联盟",
      "beneficiaries": [],
      "victims": [],
      "likelyReactions": [
        "常山阴派系监视常飚动向",
        "常飚派系加速与马家结盟"
      ],
      "confidence": "medium"
    }
  ],
  "ifBranches": [],
  "confidence": "medium",
  "sourcePointers": [
    {
      "sourcePath": "D:\\workspace\\CodeBuddyWorkSpace\\RebornG_codebuddy\\doc\\original work\\reverend-insanity.txt",
      "chapterId": "ch_0582",
      "paragraphId": "ch_0582_p0002",
      "startOffset": 2036825,
      "endOffset": 2036828,
      "summary": "马家族长，奴道蛊师"
    },
    {
      "sourcePath": "D:\\workspace\\CodeBuddyWorkSpace\\RebornG_codebuddy\\doc\\original work\\reverend-insanity.txt",
      "chapterId": "ch_0582",
      "paragraphId": "ch_0582_p0002",
      "startOffset": 2036829,
      "endOffset": 2036832,
      "summary": "马家族人，马英杰之子？"
    },
    {
      "sourcePath": "D:\\workspace\\CodeBuddyWorkSpace\\RebornG_codebuddy\\doc\\original work\\reverend-insanity.txt",
      "chapterId": "ch_0582",
      "paragraphId": "ch_0582_p0003",
      "startOffset": 2036857,
      "endOffset": 2036859,
      "summary": "常家前族长，现任大长老"
    },
    {
      "sourcePath": "D:\\workspace\\CodeBuddyWorkSpace\\RebornG_codebuddy\\doc\\original work\\reverend-insanity.txt",
      "chapterId": "ch_0582",
      "paragraphId": "ch_0582_p0003",
      "startOffset": 2036867,
      "endOffset": 2036869,
      "summary": "常家小姐"
    },
    {
      "sourcePath": "D:\\workspace\\CodeBuddyWorkSpace\\RebornG_codebuddy\\doc\\original work\\reverend-insanity.txt",
      "chapterId": "ch_0582",
      "paragraphId": "ch_0582_p0006",
      "startOffset": 2037027,
      "endOffset": 2037029,
      "summary": "黑家强者？"
    },
    {
      "sourcePath": "D:\\workspace\\CodeBuddyWorkSpace\\RebornG_codebuddy\\doc\\original work\\reverend-insanity.txt",
      "chapterId": "ch_0582",
      "paragraphId": "ch_0582_p0008",
      "startOffset": 2037081,
      "endOffset": 2037083,
      "summary": "马英杰的师傅，奴道蛊仙"
    },
    {
      "sourcePath": "D:\\workspace\\CodeBuddyWorkSpace\\RebornG_codebuddy\\doc\\original work\\reverend-insanity.txt",
      "chapterId": "ch_0582",
      "paragraphId": "ch_0582_p0018",
      "startOffset": 2037543,
      "endOffset": 2037546,
      "summary": "常家现任族长，常飚义子"
    },
    {
      "sourcePath": "D:\\workspace\\CodeBuddyWorkSpace\\RebornG_codebuddy\\doc\\original work\\reverend-insanity.txt",
      "chapterId": "ch_0582",
      "paragraphId": "ch_0582_p0018",
      "startOffset": 2037555,
      "endOffset": 2037558,
      "summary": "常家真正主事者"
    },
    {
      "sourcePath": "D:\\workspace\\CodeBuddyWorkSpace\\RebornG_codebuddy\\doc\\original work\\reverend-insanity.txt",
      "chapterId": "ch_0582",
      "paragraphId": "ch_0582_p0013",
      "startOffset": 2037281,
      "endOffset": 2037283,
      "summary": "兼修蛊师"
    },
    {
      "sourcePath": "D:\\workspace\\CodeBuddyWorkSpace\\RebornG_codebuddy\\doc\\original work\\reverend-insanity.txt",
      "chapterId": "ch_0582",
      "paragraphId": "ch_0582_p0033",
      "startOffset": 2038352,
      "endOffset": 2038379,
      "summary": "马家成员，被任命为代理长老"
    },
    {
      "sourcePath": "D:\\workspace\\CodeBuddyWorkSpace\\RebornG_codebuddy\\doc\\original work\\reverend-insanity.txt",
      "chapterId": "ch_0582",
      "paragraphId": "ch_0582_p0034",
      "startOffset": 2038383,
      "endOffset": 2038439,
      "summary": "马家族长"
    },
    {
      "sourcePath": "D:\\workspace\\CodeBuddyWorkSpace\\RebornG_codebuddy\\doc\\original work\\reverend-insanity.txt",
      "chapterId": "ch_0582",
      "paragraphId": "ch_0582_p0036",
      "startOffset": 2038472,
      "endOffset": 2038571,
      "summary": "马鸿运的成亲对象"
    },
    {
      "sourcePath": "D:\\workspace\\CodeBuddyWorkSpace\\RebornG_codebuddy\\doc\\original work\\reverend-insanity.txt",
      "chapterId": "ch_0582",
      "paragraphId": "ch_0582_p0043",
      "startOffset": 2038786,
      "endOffset": 2038812,
      "summary": "炼蛊者，掌控八十八角真阳楼"
    },
    {
      "sourcePath": "D:\\workspace\\CodeBuddyWorkSpace\\RebornG_codebuddy\\doc\\original work\\reverend-insanity.txt",
      "chapterId": "ch_0582",
      "paragraphId": "ch_0582_p0047",
      "startOffset": 2038917,
      "endOffset": 2039123,
      "summary": "方源脑海中的意志，传授炼道手法"
    },
    {
      "sourcePath": "D:\\workspace\\CodeBuddyWorkSpace\\RebornG_codebuddy\\doc\\original work\\reverend-insanity.txt",
      "chapterId": "ch_0582",
      "paragraphId": "ch_0582_p0061",
      "startOffset": 2039534,
      "endOffset": 2039613,
      "summary": "打通八十八角真阳楼第七层的蛊师之一"
    },
    {
      "sourcePath": "D:\\workspace\\CodeBuddyWorkSpace\\RebornG_codebuddy\\doc\\original work\\reverend-insanity.txt",
      "chapterId": "ch_0582",
      "paragraphId": "ch_0582_p0066",
      "startOffset": 2039828,
      "endOffset": 2039830,
      "summary": "五转蛊师，代理家老"
    },
    {
      "sourcePath": "D:\\workspace\\CodeBuddyWorkSpace\\RebornG_codebuddy\\doc\\original work\\reverend-insanity.txt",
      "chapterId": "ch_0582",
      "paragraphId": "ch_0582_p0066",
      "startOffset": 2039856,
      "endOffset": 2039861,
      "summary": "意志体，存在于方源脑海"
    },
    {
      "sourcePath": "D:\\workspace\\CodeBuddyWorkSpace\\RebornG_codebuddy\\doc\\original work\\reverend-insanity.txt",
      "chapterId": "ch_0582",
      "paragraphId": "ch_0582_p0069",
      "startOffset": 2039965,
      "endOffset": 2039967,
      "summary": "蛊师，在五转楼主第七层闯关"
    },
    {
      "sourcePath": "D:\\workspace\\CodeBuddyWorkSpace\\RebornG_codebuddy\\doc\\original work\\reverend-insanity.txt",
      "chapterId": "ch_0582",
      "paragraphId": "ch_0582_p0069",
      "startOffset": 2039970,
      "endOffset": 2039972,
      "summary": "蛊师，在五转楼主第七层闯关"
    },
    {
      "sourcePath": "D:\\workspace\\CodeBuddyWorkSpace\\RebornG_codebuddy\\doc\\original work\\reverend-insanity.txt",
      "chapterId": "ch_0582",
      "paragraphId": "ch_0582_p0025",
      "startOffset": 2037908,
      "endOffset": 2037938,
      "summary": "马英杰与常飚结盟，以兄弟相称，并约定联姻"
    },
    {
      "sourcePath": "D:\\workspace\\CodeBuddyWorkSpace\\RebornG_codebuddy\\doc\\original work\\reverend-insanity.txt",
      "chapterId": "ch_0582",
      "paragraphId": "ch_0582_p0027",
      "startOffset": 2038012,
      "endOffset": 2038020,
      "summary": "马鸿运与常丽定下婚约"
    },
    {
      "sourcePath": "D:\\workspace\\CodeBuddyWorkSpace\\RebornG_codebuddy\\doc\\original work\\reverend-insanity.txt",
      "chapterId": "ch_0582",
      "paragraphId": "ch_0582_p0029",
      "startOffset": 2038087,
      "endOffset": 2038147,
      "summary": "常飚对常山阴有异心，意图联合马英杰对抗常山阴"
    },
    {
      "sourcePath": "D:\\workspace\\CodeBuddyWorkSpace\\RebornG_codebuddy\\doc\\original work\\reverend-insanity.txt",
      "chapterId": "ch_0582",
      "paragraphId": "ch_0582_p0008",
      "startOffset": 2037059,
      "endOffset": 2037089,
      "summary": "马尊是马英杰的师傅，传授奴道传承"
    },
    {
      "sourcePath": "D:\\workspace\\CodeBuddyWorkSpace\\RebornG_codebuddy\\doc\\original work\\reverend-insanity.txt",
      "chapterId": "ch_0582",
      "paragraphId": "ch_0582_p0066",
      "startOffset": 2039828,
      "endOffset": 2039861,
      "summary": "方源与脑海中的墨瑶意志商议杀招奖励事宜"
    },
    {
      "sourcePath": "D:\\workspace\\CodeBuddyWorkSpace\\RebornG_codebuddy\\doc\\original work\\reverend-insanity.txt",
      "chapterId": "ch_0582",
      "paragraphId": "ch_0582_p0069",
      "startOffset": 2039965,
      "endOffset": 2039972,
      "summary": "常飚和潘平一同在五转楼主第七层闯关"
    },
    {
      "sourcePath": "D:\\workspace\\CodeBuddyWorkSpace\\RebornG_codebuddy\\doc\\original work\\reverend-insanity.txt",
      "chapterId": "ch_0582",
      "paragraphId": "ch_0582_p0002",
      "startOffset": 2036825,
      "endOffset": 2036845,
      "summary": "马英杰带马鸿运前往常家赴宴"
    },
    {
      "sourcePath": "D:\\workspace\\CodeBuddyWorkSpace\\RebornG_codebuddy\\doc\\original work\\reverend-insanity.txt",
      "chapterId": "ch_0582",
      "paragraphId": "ch_0582_p0003",
      "startOffset": 2036849,
      "endOffset": 2036879,
      "summary": "常飚挽留马鸿运密谈，并让常丽款待"
    },
    {
      "sourcePath": "D:\\workspace\\CodeBuddyWorkSpace\\RebornG_codebuddy\\doc\\original work\\reverend-insanity.txt",
      "chapterId": "ch_0582",
      "paragraphId": "ch_0582_p0005",
      "startOffset": 2036938,
      "endOffset": 2036978,
      "summary": "马英杰表示要贩卖六臂天尸王杀招，常飚和潘平请求保密"
    },
    {
      "sourcePath": "D:\\workspace\\CodeBuddyWorkSpace\\RebornG_codebuddy\\doc\\original work\\reverend-insanity.txt",
      "chapterId": "ch_0582",
      "paragraphId": "ch_0582_p0027",
      "startOffset": 2037996,
      "endOffset": 2038020,
      "summary": "三人密谈至深夜，定下马鸿运与常丽的婚约"
    },
    {
      "sourcePath": "D:\\workspace\\CodeBuddyWorkSpace\\RebornG_codebuddy\\doc\\original work\\reverend-insanity.txt",
      "chapterId": "ch_0582",
      "paragraphId": "ch_0582_p0051",
      "startOffset": 2039232,
      "endOffset": 2039255,
      "summary": "方源使用炼道手法骤雨，对楼主令进行第五次墨化"
    },
    {
      "sourcePath": "D:\\workspace\\CodeBuddyWorkSpace\\RebornG_codebuddy\\doc\\original work\\reverend-insanity.txt",
      "chapterId": "ch_0582",
      "paragraphId": "ch_0582_p0067",
      "startOffset": 2039891,
      "endOffset": 2039920,
      "summary": "方源与墨瑶意志商议，决定先取走两套杀招奖励，观察结果"
    },
    {
      "sourcePath": "D:\\workspace\\CodeBuddyWorkSpace\\RebornG_codebuddy\\doc\\original work\\reverend-insanity.txt",
      "chapterId": "ch_0582",
      "paragraphId": "ch_0582_p0068",
      "startOffset": 2039924,
      "endOffset": 2039961,
      "summary": "方源握住五角楼主令，发现第七层第九十关卡中有常飚和潘平"
    }
  ],
  "review": {
    "status": "needs_review",
    "classification": "hidden",
    "notes": [
      "Converted from the old chapter extraction schema.",
      "Hidden facts, motives, and faction pressures require living-world re-extraction.",
      "Merged second-stage living-world enrichment; still requires expert/manual review.",
      "insufficient source-backed seed: The seed package primarily describes visible events (banquet, alliance, marriage arrangement, cultivation of Gu, reward deduction by Fang Yuan). The relations and events are mostly player-visible or ambiguous. No directly supported hidden knowledge, secret motives beyond what is stated, or future-known information is clearly backed by the source pointers. The secret motive of Chang Biao against Chang Shanyin is stated openly in the relations (ALLY with Ma Yingjie against Chang Shanyin), so it's not a hidden fact. Fang Yuan's manipulation of the building tokens is described as an overt action. No atomic hidden fact with strong source support can be extracted.",
      "Merged second-stage living-world enrichment; still requires expert/manual review.",
      "insufficient source-backed seed",
      "The seed shows actions (马英杰结盟常飚、潘平，贩卖杀招，任命马鸿运为代理长老) but the motives behind these actions are ambiguous. While 马英杰 allies with 常飚 who has conflict with 常山阴, the seed does not directly state 马英杰's own strategic intent. Observed behavior is visible but inferred motive would require psychological leap beyond one-step cautious inference. No direct source supports a specific inferred motive like seeking power or opposing 常山阴.",
      "Merged second-stage living-world enrichment; still requires expert/manual review.",
      "马家：马英杰作为族长任命马鸿运为代理长老并赐蛊，安排与常丽联姻，涉及家族权力交接和联姻利益，有集体组织（马家）的明确行动和利益。",
      "常家：常飚（前族长/大长老）与常山阴（真正主事者）存在冲突关系，常飚联合马英杰对抗常山阴，常极右是常飚义子兼现任族长，存在内部权力斗争压力。",
      "两个压力均基于种子中的集体组织（马家、常家）及其明确利益关系，未超出种子范围。",
      "IF export filter quarantined 7 legacy old-schema branches."
    ]
  },
  "model": "deepseek-v4-flash",
  "usage": {
    "base": {
      "base": {
        "base": {
          "window_count": 3
        },
        "enrichment": {
          "tool_name": "submit_living_world_hidden_facts",
          "tool_mode": "strict",
          "tool_choice_mode": "forced"
        },
        "enrichment_model": "deepseek-v4-flash"
      },
      "enrichment": {
        "tool_name": "submit_living_world_character_motives",
        "tool_mode": "strict",
        "tool_choice_mode": "forced"
      },
      "enrichment_model": "deepseek-v4-flash"
    },
    "enrichment": {
      "tool_name": "submit_living_world_faction_pressures",
      "tool_mode": "strict",
      "tool_choice_mode": "forced"
    },
    "enrichment_model": "deepseek-v4-flash"
  }
}
