{
  "packageId": "ri_lw_ch_1700",
  "sourceRange": {
    "sourcePath": "D:\\workspace\\CodeBuddyWorkSpace\\RebornG_codebuddy\\doc\\original work\\reverend-insanity.txt",
    "chapterIds": [
      "ch_1700"
    ],
    "paragraphIds": [
      "ch_1700_p0008",
      "ch_1700_p0009",
      "ch_1700_p0011",
      "ch_1700_p0015",
      "ch_1700_p0020",
      "ch_1700_p0023",
      "ch_1700_p0025",
      "ch_1700_p0026",
      "ch_1700_p0027",
      "ch_1700_p0033",
      "ch_1700_p0036",
      "ch_1700_p0037",
      "ch_1700_p0038",
      "ch_1700_p0040",
      "ch_1700_p0041",
      "ch_1700_p0044",
      "ch_1700_p0046",
      "ch_1700_p0050",
      "ch_1700_p0053",
      "ch_1700_p0057",
      "ch_1700_p0058",
      "ch_1700_p0059",
      "ch_1700_p0060",
      "ch_1700_p0061",
      "ch_1700_p0063",
      "ch_1700_p0066",
      "ch_1700_p0068",
      "ch_1700_p0069",
      "ch_1700_p0070",
      "ch_1700_p0080",
      "ch_1700_p0083",
      "ch_1700_p0091",
      "ch_1700_p0094",
      "ch_1700_p0097",
      "ch_1700_p0102",
      "ch_1700_p0104",
      "ch_1700_p0106",
      "ch_1700_p0107",
      "ch_1700_p0112"
    ]
  },
  "entities": [
    {
      "sourcePointers": [
        {
          "sourcePath": "D:\\workspace\\CodeBuddyWorkSpace\\RebornG_codebuddy\\doc\\original work\\reverend-insanity.txt",
          "chapterId": "ch_1700",
          "paragraphId": "ch_1700_p0008",
          "startOffset": 5872476,
          "endOffset": 5872509,
          "summary": "北原黄金部族蛊仙，操控恒舟"
        }
      ],
      "entityId": "entity_cdee4c97da5b",
      "name": "冰塞川",
      "kind": "person",
      "aliases": [],
      "description": "北原黄金部族蛊仙，操控恒舟",
      "visibility": "ambiguous",
      "confidence": "medium"
    },
    {
      "sourcePointers": [
        {
          "sourcePath": "D:\\workspace\\CodeBuddyWorkSpace\\RebornG_codebuddy\\doc\\original work\\reverend-insanity.txt",
          "chapterId": "ch_1700",
          "paragraphId": "ch_1700_p0009",
          "startOffset": 5872513,
          "endOffset": 5872555,
          "summary": "蛊仙，强攻三秋黄鹤台"
        }
      ],
      "entityId": "entity_d53a83452979",
      "name": "方源",
      "kind": "person",
      "aliases": [],
      "description": "蛊仙，强攻三秋黄鹤台",
      "visibility": "ambiguous",
      "confidence": "medium"
    },
    {
      "sourcePointers": [
        {
          "sourcePath": "D:\\workspace\\CodeBuddyWorkSpace\\RebornG_codebuddy\\doc\\original work\\reverend-insanity.txt",
          "chapterId": "ch_1700",
          "paragraphId": "ch_1700_p0011",
          "startOffset": 5872585,
          "endOffset": 5872618,
          "summary": "天庭一方蛊仙，脸色铁青，奋力回援"
        }
      ],
      "entityId": "entity_b2771271dc51",
      "name": "鲨流撬上星野望",
      "kind": "person",
      "aliases": [],
      "description": "天庭一方蛊仙，脸色铁青，奋力回援",
      "visibility": "ambiguous",
      "confidence": "medium"
    },
    {
      "sourcePointers": [
        {
          "sourcePath": "D:\\workspace\\CodeBuddyWorkSpace\\RebornG_codebuddy\\doc\\original work\\reverend-insanity.txt",
          "chapterId": "ch_1700",
          "paragraphId": "ch_1700_p0020",
          "startOffset": 5872864,
          "endOffset": 5872940,
          "summary": "北原八转散仙，专修阵道，擅长模拟金木水火土五大流派，阵道大宗师，被长生天招揽"
        }
      ],
      "entityId": "entity_857266bebc76",
      "name": "五行大法师",
      "kind": "person",
      "aliases": [],
      "description": "北原八转散仙，专修阵道，擅长模拟金木水火土五大流派，阵道大宗师，被长生天招揽",
      "visibility": "ambiguous",
      "confidence": "medium"
    },
    {
      "sourcePointers": [
        {
          "sourcePath": "D:\\workspace\\CodeBuddyWorkSpace\\RebornG_codebuddy\\doc\\original work\\reverend-insanity.txt",
          "chapterId": "ch_1700",
          "paragraphId": "ch_1700_p0020",
          "startOffset": 5872864,
          "endOffset": 5872940,
          "summary": "天庭一方蛊仙，认出五行大法师"
        }
      ],
      "entityId": "entity_7c2f300572a5",
      "name": "凤九歌",
      "kind": "person",
      "aliases": [],
      "description": "天庭一方蛊仙，认出五行大法师",
      "visibility": "ambiguous",
      "confidence": "medium"
    },
    {
      "sourcePointers": [
        {
          "sourcePath": "D:\\workspace\\CodeBuddyWorkSpace\\RebornG_codebuddy\\doc\\original work\\reverend-insanity.txt",
          "chapterId": "ch_1700",
          "paragraphId": "ch_1700_p0033",
          "startOffset": 5873383,
          "endOffset": 5873464,
          "summary": "主角，拥有春秋蝉，宙道分身"
        }
      ],
      "entityId": "entity_d53a83452979",
      "name": "方源",
      "kind": "person",
      "aliases": [],
      "description": "主角，拥有春秋蝉，宙道分身",
      "visibility": "ambiguous",
      "confidence": "medium"
    },
    {
      "sourcePointers": [
        {
          "sourcePath": "D:\\workspace\\CodeBuddyWorkSpace\\RebornG_codebuddy\\doc\\original work\\reverend-insanity.txt",
          "chapterId": "ch_1700",
          "paragraphId": "ch_1700_p0036",
          "startOffset": 5873538,
          "endOffset": 5873568,
          "summary": "八转蛊仙，驾驭鲨流撬"
        }
      ],
      "entityId": "entity_f9d902a677d4",
      "name": "星野望",
      "kind": "person",
      "aliases": [],
      "description": "八转蛊仙，驾驭鲨流撬",
      "visibility": "ambiguous",
      "confidence": "medium"
    },
    {
      "sourcePointers": [
        {
          "sourcePath": "D:\\workspace\\CodeBuddyWorkSpace\\RebornG_codebuddy\\doc\\original work\\reverend-insanity.txt",
          "chapterId": "ch_1700",
          "paragraphId": "ch_1700_p0037",
          "startOffset": 5873572,
          "endOffset": 5873595,
          "summary": "长生天蛊仙，八转"
        }
      ],
      "entityId": "entity_cdee4c97da5b",
      "name": "冰塞川",
      "kind": "person",
      "aliases": [],
      "description": "长生天蛊仙，八转",
      "visibility": "ambiguous",
      "confidence": "medium"
    },
    {
      "sourcePointers": [
        {
          "sourcePath": "D:\\workspace\\CodeBuddyWorkSpace\\RebornG_codebuddy\\doc\\original work\\reverend-insanity.txt",
          "chapterId": "ch_1700",
          "paragraphId": "ch_1700_p0040",
          "startOffset": 5873684,
          "endOffset": 5873718,
          "summary": "八转蛊仙，乘坐恒舟"
        }
      ],
      "entityId": "entity_95309f1694c0",
      "name": "清夜",
      "kind": "person",
      "aliases": [],
      "description": "八转蛊仙，乘坐恒舟",
      "visibility": "ambiguous",
      "confidence": "medium"
    },
    {
      "sourcePointers": [
        {
          "sourcePath": "D:\\workspace\\CodeBuddyWorkSpace\\RebornG_codebuddy\\doc\\original work\\reverend-insanity.txt",
          "chapterId": "ch_1700",
          "paragraphId": "ch_1700_p0044",
          "startOffset": 5873855,
          "endOffset": 5873902,
          "summary": "阵道造诣惊人，布置宙道大阵"
        }
      ],
      "entityId": "entity_4d12900f7220",
      "name": "五行大法师",
      "kind": "single_person_title",
      "aliases": [],
      "description": "阵道造诣惊人，布置宙道大阵",
      "visibility": "ambiguous",
      "confidence": "medium"
    },
    {
      "sourcePointers": [
        {
          "sourcePath": "D:\\workspace\\CodeBuddyWorkSpace\\RebornG_codebuddy\\doc\\original work\\reverend-insanity.txt",
          "chapterId": "ch_1700",
          "paragraphId": "ch_1700_p0053",
          "startOffset": 5874256,
          "endOffset": 5874283,
          "summary": "坐镇三秋黄鹤台"
        }
      ],
      "entityId": "entity_7c2f300572a5",
      "name": "凤九歌",
      "kind": "person",
      "aliases": [],
      "description": "坐镇三秋黄鹤台",
      "visibility": "ambiguous",
      "confidence": "medium"
    },
    {
      "sourcePointers": [
        {
          "sourcePath": "D:\\workspace\\CodeBuddyWorkSpace\\RebornG_codebuddy\\doc\\original work\\reverend-insanity.txt",
          "chapterId": "ch_1700",
          "paragraphId": "ch_1700_p0057",
          "startOffset": 5874340,
          "endOffset": 5874384,
          "summary": "天庭援兵，八转蛊仙强者"
        }
      ],
      "entityId": "entity_3419f0deec1c",
      "name": "厉煌",
      "kind": "person",
      "aliases": [],
      "description": "天庭援兵，八转蛊仙强者",
      "visibility": "ambiguous",
      "confidence": "medium"
    },
    {
      "sourcePointers": [
        {
          "sourcePath": "D:\\workspace\\CodeBuddyWorkSpace\\RebornG_codebuddy\\doc\\original work\\reverend-insanity.txt",
          "chapterId": "ch_1700",
          "paragraphId": "ch_1700_p0058",
          "startOffset": 5874388,
          "endOffset": 5874406,
          "summary": "天庭八转蛊仙，保护凤金煌"
        }
      ],
      "entityId": "entity_e401146f6698",
      "name": "龙公",
      "kind": "person",
      "aliases": [],
      "description": "天庭八转蛊仙，保护凤金煌",
      "visibility": "ambiguous",
      "confidence": "medium"
    },
    {
      "sourcePointers": [
        {
          "sourcePath": "D:\\workspace\\CodeBuddyWorkSpace\\RebornG_codebuddy\\doc\\original work\\reverend-insanity.txt",
          "chapterId": "ch_1700",
          "paragraphId": "ch_1700_p0059",
          "startOffset": 5874410,
          "endOffset": 5874444,
          "summary": "被保护对象，周身有球形气墙"
        }
      ],
      "entityId": "entity_544246f8c2ec",
      "name": "凤金煌",
      "kind": "person",
      "aliases": [],
      "description": "被保护对象，周身有球形气墙",
      "visibility": "ambiguous",
      "confidence": "medium"
    },
    {
      "sourcePointers": [
        {
          "sourcePath": "D:\\workspace\\CodeBuddyWorkSpace\\RebornG_codebuddy\\doc\\original work\\reverend-insanity.txt",
          "chapterId": "ch_1700",
          "paragraphId": "ch_1700_p0066",
          "startOffset": 5874635,
          "endOffset": 5874661,
          "summary": "八转蛊仙，参与龙宫争夺战"
        }
      ],
      "entityId": "entity_10835da0d5be",
      "name": "青岳安",
      "kind": "person",
      "aliases": [],
      "description": "八转蛊仙，参与龙宫争夺战",
      "visibility": "ambiguous",
      "confidence": "medium"
    },
    {
      "sourcePointers": [
        {
          "sourcePath": "D:\\workspace\\CodeBuddyWorkSpace\\RebornG_codebuddy\\doc\\original work\\reverend-insanity.txt",
          "chapterId": "ch_1700",
          "paragraphId": "ch_1700_p0070",
          "startOffset": 5874800,
          "endOffset": 5874823,
          "summary": "八转蛊仙，龙宫守护者或争夺者"
        }
      ],
      "entityId": "entity_e401146f6698",
      "name": "龙公",
      "kind": "person",
      "aliases": [],
      "description": "八转蛊仙，龙宫守护者或争夺者",
      "visibility": "ambiguous",
      "confidence": "medium"
    },
    {
      "sourcePointers": [
        {
          "sourcePath": "D:\\workspace\\CodeBuddyWorkSpace\\RebornG_codebuddy\\doc\\original work\\reverend-insanity.txt",
          "chapterId": "ch_1700",
          "paragraphId": "ch_1700_p0080",
          "startOffset": 5875058,
          "endOffset": 5875087,
          "summary": "八转蛊仙，参与龙宫争夺战"
        }
      ],
      "entityId": "entity_42e8ca661c1b",
      "name": "宋启元",
      "kind": "person",
      "aliases": [],
      "description": "八转蛊仙，参与龙宫争夺战",
      "visibility": "ambiguous",
      "confidence": "medium"
    },
    {
      "sourcePointers": [
        {
          "sourcePath": "D:\\workspace\\CodeBuddyWorkSpace\\RebornG_codebuddy\\doc\\original work\\reverend-insanity.txt",
          "chapterId": "ch_1700",
          "paragraphId": "ch_1700_p0080",
          "startOffset": 5875058,
          "endOffset": 5875087,
          "summary": "八转蛊仙，参与龙宫争夺战"
        }
      ],
      "entityId": "entity_c23c19904a94",
      "name": "张阴",
      "kind": "person",
      "aliases": [],
      "description": "八转蛊仙，参与龙宫争夺战",
      "visibility": "ambiguous",
      "confidence": "medium"
    },
    {
      "sourcePointers": [
        {
          "sourcePath": "D:\\workspace\\CodeBuddyWorkSpace\\RebornG_codebuddy\\doc\\original work\\reverend-insanity.txt",
          "chapterId": "ch_1700",
          "paragraphId": "ch_1700_p0097",
          "startOffset": 5875525,
          "endOffset": 5875544,
          "summary": "准仙尊战力，龙宫争夺战参与者"
        }
      ],
      "entityId": "entity_e401146f6698",
      "name": "龙公",
      "kind": "person",
      "aliases": [],
      "description": "准仙尊战力，龙宫争夺战参与者",
      "visibility": "ambiguous",
      "confidence": "medium"
    },
    {
      "sourcePointers": [
        {
          "sourcePath": "D:\\workspace\\CodeBuddyWorkSpace\\RebornG_codebuddy\\doc\\original work\\reverend-insanity.txt",
          "chapterId": "ch_1700",
          "paragraphId": "ch_1700_p0107",
          "startOffset": 5875826,
          "endOffset": 5875870,
          "summary": "被龙公保护的对象"
        }
      ],
      "entityId": "entity_544246f8c2ec",
      "name": "凤金煌",
      "kind": "person",
      "aliases": [],
      "description": "被龙公保护的对象",
      "visibility": "ambiguous",
      "confidence": "medium"
    },
    {
      "sourcePointers": [
        {
          "sourcePath": "D:\\workspace\\CodeBuddyWorkSpace\\RebornG_codebuddy\\doc\\original work\\reverend-insanity.txt",
          "chapterId": "ch_1700",
          "paragraphId": "ch_1700_p0106",
          "startOffset": 5875768,
          "endOffset": 5875822,
          "summary": "龙宫争夺战中的对手群体"
        }
      ],
      "entityId": "entity_118357035457",
      "name": "东海八转蛊仙",
      "kind": "single_person_title",
      "aliases": [],
      "description": "龙宫争夺战中的对手群体",
      "visibility": "ambiguous",
      "confidence": "medium"
    }
  ],
  "relations": [
    {
      "sourcePointers": [
        {
          "sourcePath": "D:\\workspace\\CodeBuddyWorkSpace\\RebornG_codebuddy\\doc\\original work\\reverend-insanity.txt",
          "chapterId": "ch_1700",
          "paragraphId": "ch_1700_p0020",
          "startOffset": 5872864,
          "endOffset": 5872940,
          "summary": "五行大法师被长生天招揽"
        }
      ],
      "relationId": "rel_b1e408fbabf6",
      "subject": "五行大法师",
      "object": "长生天",
      "relationType": "FACTION",
      "summary": "五行大法师被长生天招揽",
      "timeRange": "",
      "visibility": "ambiguous",
      "confidence": "medium"
    },
    {
      "sourcePointers": [
        {
          "sourcePath": "D:\\workspace\\CodeBuddyWorkSpace\\RebornG_codebuddy\\doc\\original work\\reverend-insanity.txt",
          "chapterId": "ch_1700",
          "paragraphId": "ch_1700_p0023",
          "startOffset": 5873036,
          "endOffset": 5873059,
          "summary": "方源送给长生天关键情报"
        }
      ],
      "relationId": "rel_c3ea46a4c864",
      "subject": "方源",
      "object": "长生天",
      "relationType": "ALLY",
      "summary": "方源送给长生天关键情报",
      "timeRange": "",
      "visibility": "ambiguous",
      "confidence": "medium"
    },
    {
      "sourcePointers": [
        {
          "sourcePath": "D:\\workspace\\CodeBuddyWorkSpace\\RebornG_codebuddy\\doc\\original work\\reverend-insanity.txt",
          "chapterId": "ch_1700",
          "paragraphId": "ch_1700_p0009",
          "startOffset": 5872513,
          "endOffset": 5872555,
          "summary": "方源强攻天庭的三秋黄鹤台，并破坏镇河锁莲大阵"
        }
      ],
      "relationId": "rel_6711019af1a9",
      "subject": "方源",
      "object": "天庭",
      "relationType": "CONFLICT",
      "summary": "方源强攻天庭的三秋黄鹤台，并破坏镇河锁莲大阵",
      "timeRange": "",
      "visibility": "ambiguous",
      "confidence": "medium"
    },
    {
      "sourcePointers": [
        {
          "sourcePath": "D:\\workspace\\CodeBuddyWorkSpace\\RebornG_codebuddy\\doc\\original work\\reverend-insanity.txt",
          "chapterId": "ch_1700",
          "paragraphId": "ch_1700_p0038",
          "startOffset": 5873599,
          "endOffset": 5873630,
          "summary": "冰塞川代表长生天与方源合作，帮助方源夺取红莲真传"
        }
      ],
      "relationId": "rel_c7d8cdc0d506",
      "subject": "方源",
      "object": "冰塞川",
      "relationType": "ALLY",
      "summary": "冰塞川代表长生天与方源合作，帮助方源夺取红莲真传",
      "timeRange": "",
      "visibility": "ambiguous",
      "confidence": "medium"
    },
    {
      "sourcePointers": [
        {
          "sourcePath": "D:\\workspace\\CodeBuddyWorkSpace\\RebornG_codebuddy\\doc\\original work\\reverend-insanity.txt",
          "chapterId": "ch_1700",
          "paragraphId": "ch_1700_p0036",
          "startOffset": 5873538,
          "endOffset": 5873568,
          "summary": "星野望追杀方源"
        }
      ],
      "relationId": "rel_c710fe5f9221",
      "subject": "方源",
      "object": "星野望",
      "relationType": "CONFLICT",
      "summary": "星野望追杀方源",
      "timeRange": "",
      "visibility": "ambiguous",
      "confidence": "medium"
    },
    {
      "sourcePointers": [
        {
          "sourcePath": "D:\\workspace\\CodeBuddyWorkSpace\\RebornG_codebuddy\\doc\\original work\\reverend-insanity.txt",
          "chapterId": "ch_1700",
          "paragraphId": "ch_1700_p0037",
          "startOffset": 5873572,
          "endOffset": 5873595,
          "summary": "冰塞川阻挡星野望"
        }
      ],
      "relationId": "rel_eede58aae945",
      "subject": "冰塞川",
      "object": "星野望",
      "relationType": "CONFLICT",
      "summary": "冰塞川阻挡星野望",
      "timeRange": "",
      "visibility": "ambiguous",
      "confidence": "medium"
    },
    {
      "sourcePointers": [
        {
          "sourcePath": "D:\\workspace\\CodeBuddyWorkSpace\\RebornG_codebuddy\\doc\\original work\\reverend-insanity.txt",
          "chapterId": "ch_1700",
          "paragraphId": "ch_1700_p0041",
          "startOffset": 5873722,
          "endOffset": 5873762,
          "summary": "年关门楼阻挡清夜"
        }
      ],
      "relationId": "rel_228935be27a2",
      "subject": "清夜",
      "object": "年关门楼",
      "relationType": "CONFLICT",
      "summary": "年关门楼阻挡清夜",
      "timeRange": "",
      "visibility": "ambiguous",
      "confidence": "medium"
    },
    {
      "sourcePointers": [
        {
          "sourcePath": "D:\\workspace\\CodeBuddyWorkSpace\\RebornG_codebuddy\\doc\\original work\\reverend-insanity.txt",
          "chapterId": "ch_1700",
          "paragraphId": "ch_1700_p0060",
          "startOffset": 5874448,
          "endOffset": 5874480,
          "summary": "龙公命令厉煌保护凤金煌"
        }
      ],
      "relationId": "rel_30cd5d9a1c57",
      "subject": "龙公",
      "object": "厉煌",
      "relationType": "ALLY",
      "summary": "龙公命令厉煌保护凤金煌",
      "timeRange": "",
      "visibility": "ambiguous",
      "confidence": "medium"
    },
    {
      "sourcePointers": [
        {
          "sourcePath": "D:\\workspace\\CodeBuddyWorkSpace\\RebornG_codebuddy\\doc\\original work\\reverend-insanity.txt",
          "chapterId": "ch_1700",
          "paragraphId": "ch_1700_p0061",
          "startOffset": 5874484,
          "endOffset": 5874530,
          "summary": "厉煌负责保护凤金煌"
        }
      ],
      "relationId": "rel_e1266a27d098",
      "subject": "厉煌",
      "object": "凤金煌",
      "relationType": "ALLY",
      "summary": "厉煌负责保护凤金煌",
      "timeRange": "",
      "visibility": "ambiguous",
      "confidence": "medium"
    },
    {
      "sourcePointers": [
        {
          "sourcePath": "D:\\workspace\\CodeBuddyWorkSpace\\RebornG_codebuddy\\doc\\original work\\reverend-insanity.txt",
          "chapterId": "ch_1700",
          "paragraphId": "ch_1700_p0069",
          "startOffset": 5874758,
          "endOffset": 5874796,
          "summary": "青岳安被龙公重伤"
        }
      ],
      "relationId": "rel_c34e865af009",
      "subject": "青岳安",
      "object": "龙公",
      "relationType": "CONFLICT",
      "summary": "青岳安被龙公重伤",
      "timeRange": "",
      "visibility": "ambiguous",
      "confidence": "medium"
    },
    {
      "sourcePointers": [
        {
          "sourcePath": "D:\\workspace\\CodeBuddyWorkSpace\\RebornG_codebuddy\\doc\\original work\\reverend-insanity.txt",
          "chapterId": "ch_1700",
          "paragraphId": "ch_1700_p0080",
          "startOffset": 5875058,
          "endOffset": 5875087,
          "summary": "宋启元与张阴合力攻击龙公，但被龙公击退"
        }
      ],
      "relationId": "rel_7882b292ab53",
      "subject": "宋启元",
      "object": "龙公",
      "relationType": "CONFLICT",
      "summary": "宋启元与张阴合力攻击龙公，但被龙公击退",
      "timeRange": "",
      "visibility": "ambiguous",
      "confidence": "medium"
    },
    {
      "sourcePointers": [
        {
          "sourcePath": "D:\\workspace\\CodeBuddyWorkSpace\\RebornG_codebuddy\\doc\\original work\\reverend-insanity.txt",
          "chapterId": "ch_1700",
          "paragraphId": "ch_1700_p0080",
          "startOffset": 5875058,
          "endOffset": 5875087,
          "summary": "张阴与宋启元合力攻击龙公，但被龙公击退"
        }
      ],
      "relationId": "rel_d6ec3376a0f0",
      "subject": "张阴",
      "object": "龙公",
      "relationType": "CONFLICT",
      "summary": "张阴与宋启元合力攻击龙公，但被龙公击退",
      "timeRange": "",
      "visibility": "ambiguous",
      "confidence": "medium"
    },
    {
      "sourcePointers": [
        {
          "sourcePath": "D:\\workspace\\CodeBuddyWorkSpace\\RebornG_codebuddy\\doc\\original work\\reverend-insanity.txt",
          "chapterId": "ch_1700",
          "paragraphId": "ch_1700_p0107",
          "startOffset": 5875826,
          "endOffset": 5875870,
          "summary": "龙公保护凤金煌"
        }
      ],
      "relationId": "rel_a8247f88009d",
      "subject": "龙公",
      "object": "凤金煌",
      "relationType": "ALLY",
      "summary": "龙公保护凤金煌",
      "timeRange": "",
      "visibility": "ambiguous",
      "confidence": "medium"
    },
    {
      "sourcePointers": [
        {
          "sourcePath": "D:\\workspace\\CodeBuddyWorkSpace\\RebornG_codebuddy\\doc\\original work\\reverend-insanity.txt",
          "chapterId": "ch_1700",
          "paragraphId": "ch_1700_p0102",
          "startOffset": 5875617,
          "endOffset": 5875657,
          "summary": "龙公与东海八转蛊仙在龙宫争夺战中敌对"
        }
      ],
      "relationId": "rel_3297e24ae902",
      "subject": "龙公",
      "object": "东海八转蛊仙",
      "relationType": "CONFLICT",
      "summary": "龙公与东海八转蛊仙在龙宫争夺战中敌对",
      "timeRange": "",
      "visibility": "ambiguous",
      "confidence": "medium"
    }
  ],
  "events": [
    {
      "sourcePointers": [
        {
          "sourcePath": "D:\\workspace\\CodeBuddyWorkSpace\\RebornG_codebuddy\\doc\\original work\\reverend-insanity.txt",
          "chapterId": "ch_1700",
          "paragraphId": "ch_1700_p0009",
          "startOffset": 5872513,
          "endOffset": 5872555,
          "summary": "方源强攻三秋黄鹤台，将其打得节节败退"
        }
      ],
      "eventId": "evt_303799325ec0",
      "eventType": "conflict",
      "summary": "方源强攻三秋黄鹤台，将其打得节节败退",
      "actors": [
        "方源",
        "天庭"
      ],
      "affectedEntities": [],
      "causes": [],
      "consequences": [
        "三秋黄鹤台被压制"
      ],
      "knownObservers": [],
      "hiddenObservers": [],
      "visibility": "ambiguous",
      "confidence": "medium"
    },
    {
      "sourcePointers": [
        {
          "sourcePath": "D:\\workspace\\CodeBuddyWorkSpace\\RebornG_codebuddy\\doc\\original work\\reverend-insanity.txt",
          "chapterId": "ch_1700",
          "paragraphId": "ch_1700_p0008",
          "startOffset": 5872476,
          "endOffset": 5872509,
          "summary": "冰塞川将恒舟拍到河底离去"
        }
      ],
      "eventId": "evt_80261c0bdf82",
      "eventType": "conflict",
      "summary": "冰塞川将恒舟拍到河底离去",
      "actors": [
        "冰塞川",
        "天庭"
      ],
      "affectedEntities": [],
      "causes": [],
      "consequences": [
        "恒舟脱离战场"
      ],
      "knownObservers": [],
      "hiddenObservers": [],
      "visibility": "ambiguous",
      "confidence": "medium"
    },
    {
      "sourcePointers": [
        {
          "sourcePath": "D:\\workspace\\CodeBuddyWorkSpace\\RebornG_codebuddy\\doc\\original work\\reverend-insanity.txt",
          "chapterId": "ch_1700",
          "paragraphId": "ch_1700_p0015",
          "startOffset": 5872705,
          "endOffset": 5872737,
          "summary": "五行大法师从年关门楼中施展五行洞玄光，破坏镇河锁莲大阵"
        }
      ],
      "eventId": "evt_6d75423a1351",
      "eventType": "conflict",
      "summary": "五行大法师从年关门楼中施展五行洞玄光，破坏镇河锁莲大阵",
      "actors": [
        "五行大法师",
        "天庭"
      ],
      "affectedEntities": [],
      "causes": [],
      "consequences": [
        "镇河锁莲大阵被破坏一小半，几乎分崩瓦解，石莲岛暴露"
      ],
      "knownObservers": [],
      "hiddenObservers": [],
      "visibility": "ambiguous",
      "confidence": "medium"
    },
    {
      "sourcePointers": [
        {
          "sourcePath": "D:\\workspace\\CodeBuddyWorkSpace\\RebornG_codebuddy\\doc\\original work\\reverend-insanity.txt",
          "chapterId": "ch_1700",
          "paragraphId": "ch_1700_p0027",
          "startOffset": 5873181,
          "endOffset": 5873193,
          "summary": "方源趁大阵被破，一跃而起，踩下三秋黄鹤台，飞扑向石莲岛"
        }
      ],
      "eventId": "evt_3317ad7e5939",
      "eventType": "other",
      "summary": "方源趁大阵被破，一跃而起，踩下三秋黄鹤台，飞扑向石莲岛",
      "actors": [
        "方源"
      ],
      "affectedEntities": [],
      "causes": [],
      "consequences": [
        "方源进入石莲岛"
      ],
      "knownObservers": [],
      "hiddenObservers": [],
      "visibility": "ambiguous",
      "confidence": "medium"
    },
    {
      "sourcePointers": [
        {
          "sourcePath": "D:\\workspace\\CodeBuddyWorkSpace\\RebornG_codebuddy\\doc\\original work\\reverend-insanity.txt",
          "chapterId": "ch_1700",
          "paragraphId": "ch_1700_p0036",
          "startOffset": 5873538,
          "endOffset": 5873568,
          "summary": "星野望追杀方源，被冰塞川挡住"
        }
      ],
      "eventId": "evt_277d2f2515bf",
      "eventType": "conflict",
      "summary": "星野望追杀方源，被冰塞川挡住",
      "actors": [
        "方源",
        "星野望",
        "冰塞川"
      ],
      "affectedEntities": [],
      "causes": [],
      "consequences": [
        "方源得以继续接近石莲岛"
      ],
      "knownObservers": [],
      "hiddenObservers": [],
      "visibility": "ambiguous",
      "confidence": "medium"
    },
    {
      "sourcePointers": [
        {
          "sourcePath": "D:\\workspace\\CodeBuddyWorkSpace\\RebornG_codebuddy\\doc\\original work\\reverend-insanity.txt",
          "chapterId": "ch_1700",
          "paragraphId": "ch_1700_p0041",
          "startOffset": 5873722,
          "endOffset": 5873762,
          "summary": "年关门楼阻挡清夜，并布置宙道大阵"
        }
      ],
      "eventId": "evt_0c33a22af844",
      "eventType": "conflict",
      "summary": "年关门楼阻挡清夜，并布置宙道大阵",
      "actors": [
        "清夜",
        "年关门楼"
      ],
      "affectedEntities": [],
      "causes": [],
      "consequences": [
        "清夜被暂时阻拦"
      ],
      "knownObservers": [],
      "hiddenObservers": [],
      "visibility": "ambiguous",
      "confidence": "medium"
    },
    {
      "sourcePointers": [
        {
          "sourcePath": "D:\\workspace\\CodeBuddyWorkSpace\\RebornG_codebuddy\\doc\\original work\\reverend-insanity.txt",
          "chapterId": "ch_1700",
          "paragraphId": "ch_1700_p0046",
          "startOffset": 5873964,
          "endOffset": 5873997,
          "summary": "方源接近石莲岛时被无形巨力推开"
        }
      ],
      "eventId": "evt_8ef2736a69a5",
      "eventType": "other",
      "summary": "方源接近石莲岛时被无形巨力推开",
      "actors": [
        "方源"
      ],
      "affectedEntities": [],
      "causes": [],
      "consequences": [
        "方源未能踏上石莲岛"
      ],
      "knownObservers": [],
      "hiddenObservers": [],
      "visibility": "ambiguous",
      "confidence": "medium"
    },
    {
      "sourcePointers": [
        {
          "sourcePath": "D:\\workspace\\CodeBuddyWorkSpace\\RebornG_codebuddy\\doc\\original work\\reverend-insanity.txt",
          "chapterId": "ch_1700",
          "paragraphId": "ch_1700_p0050",
          "startOffset": 5874118,
          "endOffset": 5874174,
          "summary": "镇河锁莲大阵恢复并攻击方源"
        }
      ],
      "eventId": "evt_d772e4d00d70",
      "eventType": "conflict",
      "summary": "镇河锁莲大阵恢复并攻击方源",
      "actors": [
        "方源",
        "镇河锁莲大阵"
      ],
      "affectedEntities": [],
      "causes": [],
      "consequences": [
        "方源难以靠近石莲岛"
      ],
      "knownObservers": [],
      "hiddenObservers": [],
      "visibility": "ambiguous",
      "confidence": "medium"
    },
    {
      "sourcePointers": [
        {
          "sourcePath": "D:\\workspace\\CodeBuddyWorkSpace\\RebornG_codebuddy\\doc\\original work\\reverend-insanity.txt",
          "chapterId": "ch_1700",
          "paragraphId": "ch_1700_p0053",
          "startOffset": 5874256,
          "endOffset": 5874283,
          "summary": "凤九歌坐镇三秋黄鹤台与方源交战"
        }
      ],
      "eventId": "evt_2c0c30a5d21a",
      "eventType": "conflict",
      "summary": "凤九歌坐镇三秋黄鹤台与方源交战",
      "actors": [
        "方源",
        "凤九歌"
      ],
      "affectedEntities": [],
      "causes": [],
      "consequences": [
        "场面僵持"
      ],
      "knownObservers": [],
      "hiddenObservers": [],
      "visibility": "ambiguous",
      "confidence": "medium"
    },
    {
      "sourcePointers": [
        {
          "sourcePath": "D:\\workspace\\CodeBuddyWorkSpace\\RebornG_codebuddy\\doc\\original work\\reverend-insanity.txt",
          "chapterId": "ch_1700",
          "paragraphId": "ch_1700_p0058",
          "startOffset": 5874388,
          "endOffset": 5874406,
          "summary": "龙公将凤金煌交给厉煌保护，自己准备出手"
        }
      ],
      "eventId": "evt_a05378d00cf6",
      "eventType": "other",
      "summary": "龙公将凤金煌交给厉煌保护，自己准备出手",
      "actors": [
        "龙公",
        "厉煌",
        "凤金煌"
      ],
      "affectedEntities": [],
      "causes": [],
      "consequences": [
        "龙公即将参战"
      ],
      "knownObservers": [],
      "hiddenObservers": [],
      "visibility": "ambiguous",
      "confidence": "medium"
    },
    {
      "sourcePointers": [
        {
          "sourcePath": "D:\\workspace\\CodeBuddyWorkSpace\\RebornG_codebuddy\\doc\\original work\\reverend-insanity.txt",
          "chapterId": "ch_1700",
          "paragraphId": "ch_1700_p0068",
          "startOffset": 5874716,
          "endOffset": 5874754,
          "summary": "青岳安试图靠近龙宫，被龙公偷袭重伤"
        }
      ],
      "eventId": "evt_193a54be1e41",
      "eventType": "conflict",
      "summary": "青岳安试图靠近龙宫，被龙公偷袭重伤",
      "actors": [
        "青岳安",
        "龙公"
      ],
      "affectedEntities": [],
      "causes": [],
      "consequences": [
        "青岳安胸骨炸裂，重伤爆退"
      ],
      "knownObservers": [],
      "hiddenObservers": [],
      "visibility": "ambiguous",
      "confidence": "medium"
    },
    {
      "sourcePointers": [
        {
          "sourcePath": "D:\\workspace\\CodeBuddyWorkSpace\\RebornG_codebuddy\\doc\\original work\\reverend-insanity.txt",
          "chapterId": "ch_1700",
          "paragraphId": "ch_1700_p0083",
          "startOffset": 5875110,
          "endOffset": 5875134,
          "summary": "宋启元和张阴合力攻击龙公，被龙公以龙吼击退"
        }
      ],
      "eventId": "evt_03d54de24fa2",
      "eventType": "conflict",
      "summary": "宋启元和张阴合力攻击龙公，被龙公以龙吼击退",
      "actors": [
        "龙公",
        "宋启元",
        "张阴"
      ],
      "affectedEntities": [],
      "causes": [],
      "consequences": [
        "宋启元、张阴倒飞出去，被打败"
      ],
      "knownObservers": [],
      "hiddenObservers": [],
      "visibility": "ambiguous",
      "confidence": "medium"
    },
    {
      "sourcePointers": [
        {
          "sourcePath": "D:\\workspace\\CodeBuddyWorkSpace\\RebornG_codebuddy\\doc\\original work\\reverend-insanity.txt",
          "chapterId": "ch_1700",
          "paragraphId": "ch_1700_p0091",
          "startOffset": 5875325,
          "endOffset": 5875336,
          "summary": "龙公施展仙道杀招气盖山河，压制所有八转蛊仙和龙宫"
        }
      ],
      "eventId": "evt_e1d8635f206a",
      "eventType": "conflict",
      "summary": "龙公施展仙道杀招气盖山河，压制所有八转蛊仙和龙宫",
      "actors": [
        "龙公",
        "众八转蛊仙"
      ],
      "affectedEntities": [],
      "causes": [],
      "consequences": [
        "众八转蛊仙连同龙宫落入水中，天地镇静"
      ],
      "knownObservers": [],
      "hiddenObservers": [],
      "visibility": "ambiguous",
      "confidence": "medium"
    },
    {
      "sourcePointers": [
        {
          "sourcePath": "D:\\workspace\\CodeBuddyWorkSpace\\RebornG_codebuddy\\doc\\original work\\reverend-insanity.txt",
          "chapterId": "ch_1700",
          "paragraphId": "ch_1700_p0097",
          "startOffset": 5875525,
          "endOffset": 5875544,
          "summary": "龙公在龙宫争夺战中施展真正实力，以准仙尊战力压制东海八转蛊仙"
        }
      ],
      "eventId": "evt_cffcc34281bb",
      "eventType": "conflict",
      "summary": "龙公在龙宫争夺战中施展真正实力，以准仙尊战力压制东海八转蛊仙",
      "actors": [
        "龙公",
        "东海八转蛊仙"
      ],
      "affectedEntities": [],
      "causes": [],
      "consequences": [
        "东海八转蛊仙被压制，龙公占据上风"
      ],
      "knownObservers": [],
      "hiddenObservers": [],
      "visibility": "ambiguous",
      "confidence": "medium"
    },
    {
      "sourcePointers": [
        {
          "sourcePath": "D:\\workspace\\CodeBuddyWorkSpace\\RebornG_codebuddy\\doc\\original work\\reverend-insanity.txt",
          "chapterId": "ch_1700",
          "paragraphId": "ch_1700_p0104",
          "startOffset": 5875696,
          "endOffset": 5875712,
          "summary": "龙公使用仙道杀招龙啸波和近战攻击，击退东海八转蛊仙"
        }
      ],
      "eventId": "evt_3317946d2018",
      "eventType": "conflict",
      "summary": "龙公使用仙道杀招龙啸波和近战攻击，击退东海八转蛊仙",
      "actors": [
        "龙公",
        "东海八转蛊仙"
      ],
      "affectedEntities": [],
      "causes": [],
      "consequences": [
        "东海八转蛊仙被击退到海水深处"
      ],
      "knownObservers": [],
      "hiddenObservers": [],
      "visibility": "ambiguous",
      "confidence": "medium"
    },
    {
      "sourcePointers": [
        {
          "sourcePath": "D:\\workspace\\CodeBuddyWorkSpace\\RebornG_codebuddy\\doc\\original work\\reverend-insanity.txt",
          "chapterId": "ch_1700",
          "paragraphId": "ch_1700_p0112",
          "startOffset": 5875946,
          "endOffset": 5875957,
          "summary": "龙公使用仙道杀招气盖山河，将东海八转蛊仙压入海水深处"
        }
      ],
      "eventId": "evt_3bde9f46e74e",
      "eventType": "conflict",
      "summary": "龙公使用仙道杀招气盖山河，将东海八转蛊仙压入海水深处",
      "actors": [
        "龙公",
        "东海八转蛊仙"
      ],
      "affectedEntities": [],
      "causes": [],
      "consequences": [
        "东海八转蛊仙再次被压制"
      ],
      "knownObservers": [],
      "hiddenObservers": [],
      "visibility": "ambiguous",
      "confidence": "medium"
    }
  ],
  "timeline": [
    {
      "sourcePointers": [
        {
          "sourcePath": "D:\\workspace\\CodeBuddyWorkSpace\\RebornG_codebuddy\\doc\\original work\\reverend-insanity.txt",
          "chapterId": "ch_1700",
          "paragraphId": "ch_1700_p0009",
          "startOffset": 5872513,
          "endOffset": 5872555,
          "summary": "方源强攻三秋黄鹤台，将其打得节节败退"
        }
      ],
      "timelineId": "tl_303799325ec0",
      "eventId": "evt_303799325ec0",
      "chapterId": "ch_1700",
      "orderHint": "chapter-order",
      "summary": "方源强攻三秋黄鹤台，将其打得节节败退",
      "confidence": "medium"
    },
    {
      "sourcePointers": [
        {
          "sourcePath": "D:\\workspace\\CodeBuddyWorkSpace\\RebornG_codebuddy\\doc\\original work\\reverend-insanity.txt",
          "chapterId": "ch_1700",
          "paragraphId": "ch_1700_p0008",
          "startOffset": 5872476,
          "endOffset": 5872509,
          "summary": "冰塞川将恒舟拍到河底离去"
        }
      ],
      "timelineId": "tl_80261c0bdf82",
      "eventId": "evt_80261c0bdf82",
      "chapterId": "ch_1700",
      "orderHint": "chapter-order",
      "summary": "冰塞川将恒舟拍到河底离去",
      "confidence": "medium"
    },
    {
      "sourcePointers": [
        {
          "sourcePath": "D:\\workspace\\CodeBuddyWorkSpace\\RebornG_codebuddy\\doc\\original work\\reverend-insanity.txt",
          "chapterId": "ch_1700",
          "paragraphId": "ch_1700_p0015",
          "startOffset": 5872705,
          "endOffset": 5872737,
          "summary": "五行大法师从年关门楼中施展五行洞玄光，破坏镇河锁莲大阵"
        }
      ],
      "timelineId": "tl_6d75423a1351",
      "eventId": "evt_6d75423a1351",
      "chapterId": "ch_1700",
      "orderHint": "chapter-order",
      "summary": "五行大法师从年关门楼中施展五行洞玄光，破坏镇河锁莲大阵",
      "confidence": "medium"
    },
    {
      "sourcePointers": [
        {
          "sourcePath": "D:\\workspace\\CodeBuddyWorkSpace\\RebornG_codebuddy\\doc\\original work\\reverend-insanity.txt",
          "chapterId": "ch_1700",
          "paragraphId": "ch_1700_p0027",
          "startOffset": 5873181,
          "endOffset": 5873193,
          "summary": "方源趁大阵被破，一跃而起，踩下三秋黄鹤台，飞扑向石莲岛"
        }
      ],
      "timelineId": "tl_3317ad7e5939",
      "eventId": "evt_3317ad7e5939",
      "chapterId": "ch_1700",
      "orderHint": "chapter-order",
      "summary": "方源趁大阵被破，一跃而起，踩下三秋黄鹤台，飞扑向石莲岛",
      "confidence": "medium"
    },
    {
      "sourcePointers": [
        {
          "sourcePath": "D:\\workspace\\CodeBuddyWorkSpace\\RebornG_codebuddy\\doc\\original work\\reverend-insanity.txt",
          "chapterId": "ch_1700",
          "paragraphId": "ch_1700_p0036",
          "startOffset": 5873538,
          "endOffset": 5873568,
          "summary": "星野望追杀方源，被冰塞川挡住"
        }
      ],
      "timelineId": "tl_277d2f2515bf",
      "eventId": "evt_277d2f2515bf",
      "chapterId": "ch_1700",
      "orderHint": "chapter-order",
      "summary": "星野望追杀方源，被冰塞川挡住",
      "confidence": "medium"
    },
    {
      "sourcePointers": [
        {
          "sourcePath": "D:\\workspace\\CodeBuddyWorkSpace\\RebornG_codebuddy\\doc\\original work\\reverend-insanity.txt",
          "chapterId": "ch_1700",
          "paragraphId": "ch_1700_p0041",
          "startOffset": 5873722,
          "endOffset": 5873762,
          "summary": "年关门楼阻挡清夜，并布置宙道大阵"
        }
      ],
      "timelineId": "tl_0c33a22af844",
      "eventId": "evt_0c33a22af844",
      "chapterId": "ch_1700",
      "orderHint": "chapter-order",
      "summary": "年关门楼阻挡清夜，并布置宙道大阵",
      "confidence": "medium"
    },
    {
      "sourcePointers": [
        {
          "sourcePath": "D:\\workspace\\CodeBuddyWorkSpace\\RebornG_codebuddy\\doc\\original work\\reverend-insanity.txt",
          "chapterId": "ch_1700",
          "paragraphId": "ch_1700_p0046",
          "startOffset": 5873964,
          "endOffset": 5873997,
          "summary": "方源接近石莲岛时被无形巨力推开"
        }
      ],
      "timelineId": "tl_8ef2736a69a5",
      "eventId": "evt_8ef2736a69a5",
      "chapterId": "ch_1700",
      "orderHint": "chapter-order",
      "summary": "方源接近石莲岛时被无形巨力推开",
      "confidence": "medium"
    },
    {
      "sourcePointers": [
        {
          "sourcePath": "D:\\workspace\\CodeBuddyWorkSpace\\RebornG_codebuddy\\doc\\original work\\reverend-insanity.txt",
          "chapterId": "ch_1700",
          "paragraphId": "ch_1700_p0050",
          "startOffset": 5874118,
          "endOffset": 5874174,
          "summary": "镇河锁莲大阵恢复并攻击方源"
        }
      ],
      "timelineId": "tl_d772e4d00d70",
      "eventId": "evt_d772e4d00d70",
      "chapterId": "ch_1700",
      "orderHint": "chapter-order",
      "summary": "镇河锁莲大阵恢复并攻击方源",
      "confidence": "medium"
    },
    {
      "sourcePointers": [
        {
          "sourcePath": "D:\\workspace\\CodeBuddyWorkSpace\\RebornG_codebuddy\\doc\\original work\\reverend-insanity.txt",
          "chapterId": "ch_1700",
          "paragraphId": "ch_1700_p0053",
          "startOffset": 5874256,
          "endOffset": 5874283,
          "summary": "凤九歌坐镇三秋黄鹤台与方源交战"
        }
      ],
      "timelineId": "tl_2c0c30a5d21a",
      "eventId": "evt_2c0c30a5d21a",
      "chapterId": "ch_1700",
      "orderHint": "chapter-order",
      "summary": "凤九歌坐镇三秋黄鹤台与方源交战",
      "confidence": "medium"
    },
    {
      "sourcePointers": [
        {
          "sourcePath": "D:\\workspace\\CodeBuddyWorkSpace\\RebornG_codebuddy\\doc\\original work\\reverend-insanity.txt",
          "chapterId": "ch_1700",
          "paragraphId": "ch_1700_p0058",
          "startOffset": 5874388,
          "endOffset": 5874406,
          "summary": "龙公将凤金煌交给厉煌保护，自己准备出手"
        }
      ],
      "timelineId": "tl_a05378d00cf6",
      "eventId": "evt_a05378d00cf6",
      "chapterId": "ch_1700",
      "orderHint": "chapter-order",
      "summary": "龙公将凤金煌交给厉煌保护，自己准备出手",
      "confidence": "medium"
    },
    {
      "sourcePointers": [
        {
          "sourcePath": "D:\\workspace\\CodeBuddyWorkSpace\\RebornG_codebuddy\\doc\\original work\\reverend-insanity.txt",
          "chapterId": "ch_1700",
          "paragraphId": "ch_1700_p0068",
          "startOffset": 5874716,
          "endOffset": 5874754,
          "summary": "青岳安试图靠近龙宫，被龙公偷袭重伤"
        }
      ],
      "timelineId": "tl_193a54be1e41",
      "eventId": "evt_193a54be1e41",
      "chapterId": "ch_1700",
      "orderHint": "chapter-order",
      "summary": "青岳安试图靠近龙宫，被龙公偷袭重伤",
      "confidence": "medium"
    },
    {
      "sourcePointers": [
        {
          "sourcePath": "D:\\workspace\\CodeBuddyWorkSpace\\RebornG_codebuddy\\doc\\original work\\reverend-insanity.txt",
          "chapterId": "ch_1700",
          "paragraphId": "ch_1700_p0083",
          "startOffset": 5875110,
          "endOffset": 5875134,
          "summary": "宋启元和张阴合力攻击龙公，被龙公以龙吼击退"
        }
      ],
      "timelineId": "tl_03d54de24fa2",
      "eventId": "evt_03d54de24fa2",
      "chapterId": "ch_1700",
      "orderHint": "chapter-order",
      "summary": "宋启元和张阴合力攻击龙公，被龙公以龙吼击退",
      "confidence": "medium"
    },
    {
      "sourcePointers": [
        {
          "sourcePath": "D:\\workspace\\CodeBuddyWorkSpace\\RebornG_codebuddy\\doc\\original work\\reverend-insanity.txt",
          "chapterId": "ch_1700",
          "paragraphId": "ch_1700_p0091",
          "startOffset": 5875325,
          "endOffset": 5875336,
          "summary": "龙公施展仙道杀招气盖山河，压制所有八转蛊仙和龙宫"
        }
      ],
      "timelineId": "tl_e1d8635f206a",
      "eventId": "evt_e1d8635f206a",
      "chapterId": "ch_1700",
      "orderHint": "chapter-order",
      "summary": "龙公施展仙道杀招气盖山河，压制所有八转蛊仙和龙宫",
      "confidence": "medium"
    },
    {
      "sourcePointers": [
        {
          "sourcePath": "D:\\workspace\\CodeBuddyWorkSpace\\RebornG_codebuddy\\doc\\original work\\reverend-insanity.txt",
          "chapterId": "ch_1700",
          "paragraphId": "ch_1700_p0097",
          "startOffset": 5875525,
          "endOffset": 5875544,
          "summary": "龙公在龙宫争夺战中施展真正实力，以准仙尊战力压制东海八转蛊仙"
        }
      ],
      "timelineId": "tl_cffcc34281bb",
      "eventId": "evt_cffcc34281bb",
      "chapterId": "ch_1700",
      "orderHint": "chapter-order",
      "summary": "龙公在龙宫争夺战中施展真正实力，以准仙尊战力压制东海八转蛊仙",
      "confidence": "medium"
    },
    {
      "sourcePointers": [
        {
          "sourcePath": "D:\\workspace\\CodeBuddyWorkSpace\\RebornG_codebuddy\\doc\\original work\\reverend-insanity.txt",
          "chapterId": "ch_1700",
          "paragraphId": "ch_1700_p0104",
          "startOffset": 5875696,
          "endOffset": 5875712,
          "summary": "龙公使用仙道杀招龙啸波和近战攻击，击退东海八转蛊仙"
        }
      ],
      "timelineId": "tl_3317946d2018",
      "eventId": "evt_3317946d2018",
      "chapterId": "ch_1700",
      "orderHint": "chapter-order",
      "summary": "龙公使用仙道杀招龙啸波和近战攻击，击退东海八转蛊仙",
      "confidence": "medium"
    },
    {
      "sourcePointers": [
        {
          "sourcePath": "D:\\workspace\\CodeBuddyWorkSpace\\RebornG_codebuddy\\doc\\original work\\reverend-insanity.txt",
          "chapterId": "ch_1700",
          "paragraphId": "ch_1700_p0112",
          "startOffset": 5875946,
          "endOffset": 5875957,
          "summary": "龙公使用仙道杀招气盖山河，将东海八转蛊仙压入海水深处"
        }
      ],
      "timelineId": "tl_3bde9f46e74e",
      "eventId": "evt_3bde9f46e74e",
      "chapterId": "ch_1700",
      "orderHint": "chapter-order",
      "summary": "龙公使用仙道杀招气盖山河，将东海八转蛊仙压入海水深处",
      "confidence": "medium"
    }
  ],
  "hiddenFacts": [],
  "characterMotives": [],
  "factionPressures": [],
  "ifBranches": [],
  "confidence": "medium",
  "sourcePointers": [
    {
      "sourcePath": "D:\\workspace\\CodeBuddyWorkSpace\\RebornG_codebuddy\\doc\\original work\\reverend-insanity.txt",
      "chapterId": "ch_1700",
      "paragraphId": "ch_1700_p0008",
      "startOffset": 5872476,
      "endOffset": 5872509,
      "summary": "北原黄金部族蛊仙，操控恒舟"
    },
    {
      "sourcePath": "D:\\workspace\\CodeBuddyWorkSpace\\RebornG_codebuddy\\doc\\original work\\reverend-insanity.txt",
      "chapterId": "ch_1700",
      "paragraphId": "ch_1700_p0009",
      "startOffset": 5872513,
      "endOffset": 5872555,
      "summary": "蛊仙，强攻三秋黄鹤台"
    },
    {
      "sourcePath": "D:\\workspace\\CodeBuddyWorkSpace\\RebornG_codebuddy\\doc\\original work\\reverend-insanity.txt",
      "chapterId": "ch_1700",
      "paragraphId": "ch_1700_p0011",
      "startOffset": 5872585,
      "endOffset": 5872618,
      "summary": "天庭一方蛊仙，脸色铁青，奋力回援"
    },
    {
      "sourcePath": "D:\\workspace\\CodeBuddyWorkSpace\\RebornG_codebuddy\\doc\\original work\\reverend-insanity.txt",
      "chapterId": "ch_1700",
      "paragraphId": "ch_1700_p0020",
      "startOffset": 5872864,
      "endOffset": 5872940,
      "summary": "北原八转散仙，专修阵道，擅长模拟金木水火土五大流派，阵道大宗师，被长生天招揽"
    },
    {
      "sourcePath": "D:\\workspace\\CodeBuddyWorkSpace\\RebornG_codebuddy\\doc\\original work\\reverend-insanity.txt",
      "chapterId": "ch_1700",
      "paragraphId": "ch_1700_p0033",
      "startOffset": 5873383,
      "endOffset": 5873464,
      "summary": "主角，拥有春秋蝉，宙道分身"
    },
    {
      "sourcePath": "D:\\workspace\\CodeBuddyWorkSpace\\RebornG_codebuddy\\doc\\original work\\reverend-insanity.txt",
      "chapterId": "ch_1700",
      "paragraphId": "ch_1700_p0036",
      "startOffset": 5873538,
      "endOffset": 5873568,
      "summary": "八转蛊仙，驾驭鲨流撬"
    },
    {
      "sourcePath": "D:\\workspace\\CodeBuddyWorkSpace\\RebornG_codebuddy\\doc\\original work\\reverend-insanity.txt",
      "chapterId": "ch_1700",
      "paragraphId": "ch_1700_p0037",
      "startOffset": 5873572,
      "endOffset": 5873595,
      "summary": "长生天蛊仙，八转"
    },
    {
      "sourcePath": "D:\\workspace\\CodeBuddyWorkSpace\\RebornG_codebuddy\\doc\\original work\\reverend-insanity.txt",
      "chapterId": "ch_1700",
      "paragraphId": "ch_1700_p0040",
      "startOffset": 5873684,
      "endOffset": 5873718,
      "summary": "八转蛊仙，乘坐恒舟"
    },
    {
      "sourcePath": "D:\\workspace\\CodeBuddyWorkSpace\\RebornG_codebuddy\\doc\\original work\\reverend-insanity.txt",
      "chapterId": "ch_1700",
      "paragraphId": "ch_1700_p0044",
      "startOffset": 5873855,
      "endOffset": 5873902,
      "summary": "阵道造诣惊人，布置宙道大阵"
    },
    {
      "sourcePath": "D:\\workspace\\CodeBuddyWorkSpace\\RebornG_codebuddy\\doc\\original work\\reverend-insanity.txt",
      "chapterId": "ch_1700",
      "paragraphId": "ch_1700_p0053",
      "startOffset": 5874256,
      "endOffset": 5874283,
      "summary": "坐镇三秋黄鹤台"
    },
    {
      "sourcePath": "D:\\workspace\\CodeBuddyWorkSpace\\RebornG_codebuddy\\doc\\original work\\reverend-insanity.txt",
      "chapterId": "ch_1700",
      "paragraphId": "ch_1700_p0057",
      "startOffset": 5874340,
      "endOffset": 5874384,
      "summary": "天庭援兵，八转蛊仙强者"
    },
    {
      "sourcePath": "D:\\workspace\\CodeBuddyWorkSpace\\RebornG_codebuddy\\doc\\original work\\reverend-insanity.txt",
      "chapterId": "ch_1700",
      "paragraphId": "ch_1700_p0058",
      "startOffset": 5874388,
      "endOffset": 5874406,
      "summary": "天庭八转蛊仙，保护凤金煌"
    },
    {
      "sourcePath": "D:\\workspace\\CodeBuddyWorkSpace\\RebornG_codebuddy\\doc\\original work\\reverend-insanity.txt",
      "chapterId": "ch_1700",
      "paragraphId": "ch_1700_p0059",
      "startOffset": 5874410,
      "endOffset": 5874444,
      "summary": "被保护对象，周身有球形气墙"
    },
    {
      "sourcePath": "D:\\workspace\\CodeBuddyWorkSpace\\RebornG_codebuddy\\doc\\original work\\reverend-insanity.txt",
      "chapterId": "ch_1700",
      "paragraphId": "ch_1700_p0066",
      "startOffset": 5874635,
      "endOffset": 5874661,
      "summary": "八转蛊仙，参与龙宫争夺战"
    },
    {
      "sourcePath": "D:\\workspace\\CodeBuddyWorkSpace\\RebornG_codebuddy\\doc\\original work\\reverend-insanity.txt",
      "chapterId": "ch_1700",
      "paragraphId": "ch_1700_p0070",
      "startOffset": 5874800,
      "endOffset": 5874823,
      "summary": "八转蛊仙，龙宫守护者或争夺者"
    },
    {
      "sourcePath": "D:\\workspace\\CodeBuddyWorkSpace\\RebornG_codebuddy\\doc\\original work\\reverend-insanity.txt",
      "chapterId": "ch_1700",
      "paragraphId": "ch_1700_p0080",
      "startOffset": 5875058,
      "endOffset": 5875087,
      "summary": "八转蛊仙，参与龙宫争夺战"
    },
    {
      "sourcePath": "D:\\workspace\\CodeBuddyWorkSpace\\RebornG_codebuddy\\doc\\original work\\reverend-insanity.txt",
      "chapterId": "ch_1700",
      "paragraphId": "ch_1700_p0097",
      "startOffset": 5875525,
      "endOffset": 5875544,
      "summary": "准仙尊战力，龙宫争夺战参与者"
    },
    {
      "sourcePath": "D:\\workspace\\CodeBuddyWorkSpace\\RebornG_codebuddy\\doc\\original work\\reverend-insanity.txt",
      "chapterId": "ch_1700",
      "paragraphId": "ch_1700_p0107",
      "startOffset": 5875826,
      "endOffset": 5875870,
      "summary": "被龙公保护的对象"
    },
    {
      "sourcePath": "D:\\workspace\\CodeBuddyWorkSpace\\RebornG_codebuddy\\doc\\original work\\reverend-insanity.txt",
      "chapterId": "ch_1700",
      "paragraphId": "ch_1700_p0106",
      "startOffset": 5875768,
      "endOffset": 5875822,
      "summary": "龙宫争夺战中的对手群体"
    },
    {
      "sourcePath": "D:\\workspace\\CodeBuddyWorkSpace\\RebornG_codebuddy\\doc\\original work\\reverend-insanity.txt",
      "chapterId": "ch_1700",
      "paragraphId": "ch_1700_p0023",
      "startOffset": 5873036,
      "endOffset": 5873059,
      "summary": "方源送给长生天关键情报"
    },
    {
      "sourcePath": "D:\\workspace\\CodeBuddyWorkSpace\\RebornG_codebuddy\\doc\\original work\\reverend-insanity.txt",
      "chapterId": "ch_1700",
      "paragraphId": "ch_1700_p0038",
      "startOffset": 5873599,
      "endOffset": 5873630,
      "summary": "冰塞川代表长生天与方源合作，帮助方源夺取红莲真传"
    },
    {
      "sourcePath": "D:\\workspace\\CodeBuddyWorkSpace\\RebornG_codebuddy\\doc\\original work\\reverend-insanity.txt",
      "chapterId": "ch_1700",
      "paragraphId": "ch_1700_p0041",
      "startOffset": 5873722,
      "endOffset": 5873762,
      "summary": "年关门楼阻挡清夜"
    },
    {
      "sourcePath": "D:\\workspace\\CodeBuddyWorkSpace\\RebornG_codebuddy\\doc\\original work\\reverend-insanity.txt",
      "chapterId": "ch_1700",
      "paragraphId": "ch_1700_p0060",
      "startOffset": 5874448,
      "endOffset": 5874480,
      "summary": "龙公命令厉煌保护凤金煌"
    },
    {
      "sourcePath": "D:\\workspace\\CodeBuddyWorkSpace\\RebornG_codebuddy\\doc\\original work\\reverend-insanity.txt",
      "chapterId": "ch_1700",
      "paragraphId": "ch_1700_p0061",
      "startOffset": 5874484,
      "endOffset": 5874530,
      "summary": "厉煌负责保护凤金煌"
    },
    {
      "sourcePath": "D:\\workspace\\CodeBuddyWorkSpace\\RebornG_codebuddy\\doc\\original work\\reverend-insanity.txt",
      "chapterId": "ch_1700",
      "paragraphId": "ch_1700_p0069",
      "startOffset": 5874758,
      "endOffset": 5874796,
      "summary": "青岳安被龙公重伤"
    },
    {
      "sourcePath": "D:\\workspace\\CodeBuddyWorkSpace\\RebornG_codebuddy\\doc\\original work\\reverend-insanity.txt",
      "chapterId": "ch_1700",
      "paragraphId": "ch_1700_p0102",
      "startOffset": 5875617,
      "endOffset": 5875657,
      "summary": "龙公与东海八转蛊仙在龙宫争夺战中敌对"
    },
    {
      "sourcePath": "D:\\workspace\\CodeBuddyWorkSpace\\RebornG_codebuddy\\doc\\original work\\reverend-insanity.txt",
      "chapterId": "ch_1700",
      "paragraphId": "ch_1700_p0015",
      "startOffset": 5872705,
      "endOffset": 5872737,
      "summary": "五行大法师从年关门楼中施展五行洞玄光，破坏镇河锁莲大阵"
    },
    {
      "sourcePath": "D:\\workspace\\CodeBuddyWorkSpace\\RebornG_codebuddy\\doc\\original work\\reverend-insanity.txt",
      "chapterId": "ch_1700",
      "paragraphId": "ch_1700_p0027",
      "startOffset": 5873181,
      "endOffset": 5873193,
      "summary": "方源趁大阵被破，一跃而起，踩下三秋黄鹤台，飞扑向石莲岛"
    },
    {
      "sourcePath": "D:\\workspace\\CodeBuddyWorkSpace\\RebornG_codebuddy\\doc\\original work\\reverend-insanity.txt",
      "chapterId": "ch_1700",
      "paragraphId": "ch_1700_p0046",
      "startOffset": 5873964,
      "endOffset": 5873997,
      "summary": "方源接近石莲岛时被无形巨力推开"
    },
    {
      "sourcePath": "D:\\workspace\\CodeBuddyWorkSpace\\RebornG_codebuddy\\doc\\original work\\reverend-insanity.txt",
      "chapterId": "ch_1700",
      "paragraphId": "ch_1700_p0050",
      "startOffset": 5874118,
      "endOffset": 5874174,
      "summary": "镇河锁莲大阵恢复并攻击方源"
    },
    {
      "sourcePath": "D:\\workspace\\CodeBuddyWorkSpace\\RebornG_codebuddy\\doc\\original work\\reverend-insanity.txt",
      "chapterId": "ch_1700",
      "paragraphId": "ch_1700_p0068",
      "startOffset": 5874716,
      "endOffset": 5874754,
      "summary": "青岳安试图靠近龙宫，被龙公偷袭重伤"
    },
    {
      "sourcePath": "D:\\workspace\\CodeBuddyWorkSpace\\RebornG_codebuddy\\doc\\original work\\reverend-insanity.txt",
      "chapterId": "ch_1700",
      "paragraphId": "ch_1700_p0083",
      "startOffset": 5875110,
      "endOffset": 5875134,
      "summary": "宋启元和张阴合力攻击龙公，被龙公以龙吼击退"
    },
    {
      "sourcePath": "D:\\workspace\\CodeBuddyWorkSpace\\RebornG_codebuddy\\doc\\original work\\reverend-insanity.txt",
      "chapterId": "ch_1700",
      "paragraphId": "ch_1700_p0091",
      "startOffset": 5875325,
      "endOffset": 5875336,
      "summary": "龙公施展仙道杀招气盖山河，压制所有八转蛊仙和龙宫"
    },
    {
      "sourcePath": "D:\\workspace\\CodeBuddyWorkSpace\\RebornG_codebuddy\\doc\\original work\\reverend-insanity.txt",
      "chapterId": "ch_1700",
      "paragraphId": "ch_1700_p0104",
      "startOffset": 5875696,
      "endOffset": 5875712,
      "summary": "龙公使用仙道杀招龙啸波和近战攻击，击退东海八转蛊仙"
    },
    {
      "sourcePath": "D:\\workspace\\CodeBuddyWorkSpace\\RebornG_codebuddy\\doc\\original work\\reverend-insanity.txt",
      "chapterId": "ch_1700",
      "paragraphId": "ch_1700_p0112",
      "startOffset": 5875946,
      "endOffset": 5875957,
      "summary": "龙公使用仙道杀招气盖山河，将东海八转蛊仙压入海水深处"
    }
  ],
  "review": {
    "status": "needs_review",
    "classification": "hidden",
    "notes": [
      "Converted from the old chapter extraction schema.",
      "Hidden facts, motives, and faction pressures require living-world re-extraction.",
      "Merged second-stage living-world enrichment; still requires expert/manual review.",
      "insufficient source-backed seed: The seed package describes an ongoing battle scene (方源 attacking 三秋黄鹤台, 五行大法师 breaking the formation, 冰塞川 blocking 星野望, etc.) with mostly public/visible combat events. No private knowledge, secret plans, or future-known information is directly supported by the source pointers. The entities and events are all observable actions during a battle. There is no source-backed hidden fact such as a character's secret motive, undisclosed plan, or knowledge gap that can be extracted as an atomic hidden fact without speculation.",
      "Merged second-stage living-world enrichment; still requires expert/manual review.",
      "insufficient source-backed seed",
      "The seed package contains mostly combat actions and positional movements (方源强攻三秋黄鹤台, 冰塞川阻挡星野望, 五行大法师破坏大阵, etc.) but no direct source text that reveals a character's internal motive or intent behind an action. Observed behaviors are visible (e.g., 方源强攻, 冰塞川阻挡, 五行大法师施展五行洞玄光) but the inferred motive would require a psychological leap beyond one-step cautious inference. For example, 五行大法师破坏镇河锁莲大阵 could be observed, but inferring why (e.g., to help 方源 enter 石莲岛) is not directly supported by seed text. Similarly, 冰塞川阻挡星野望 is observed but the motive (e.g., to help 方源) is ambiguous without direct source backing. Returning empty set per rules.",
      "Merged second-stage living-world enrichment; still requires expert/manual review.",
      "insufficient source-backed seed: The seed contains many individual actors (方源, 冰塞川, 星野望, 五行大法师, 凤九歌, etc.) but the only named collective factions are 长生天 (Longevity Heaven) and 天庭 (Heavenly Court). While 五行大法师 is recruited by 长生天 and 方源 is allied with 长生天, and 天庭 is in conflict with 方源, the seed facts describe a single battle scene (三秋黄鹤台 assault, 石莲岛 approach) with no clear ongoing faction-level pressure dynamics that are source-backed. The events are immediate combat actions, not sustained faction pressures. No named family, clan, shop, hall, or other collective group beyond the two major factions has a concrete stake described in the seed. The individual conflicts (星野望 vs 方源, 冰塞川 vs 星野望) are personal combat encounters within a larger battle, not faction-level pressure axes. No succession, inheritance, resource, reputation, or geographic pressure is clearly source-backed for any collective actor.",
      "IF export filter quarantined 7 legacy old-schema branches."
    ]
  },
  "model": "deepseek-v4-flash",
  "usage": {
    "base": {
      "base": {
        "base": {
          "window_count": 4
        },
        "enrichment": {
          "tool_name": "submit_living_world_hidden_facts",
          "tool_mode": "strict",
          "tool_choice_mode": "forced"
        },
        "enrichment_model": "deepseek-v4-flash"
      },
      "enrichment": {
        "tool_name": "submit_living_world_character_motives",
        "tool_mode": "strict",
        "tool_choice_mode": "forced"
      },
      "enrichment_model": "deepseek-v4-flash"
    },
    "enrichment": {
      "tool_name": "submit_living_world_faction_pressures",
      "tool_mode": "strict",
      "tool_choice_mode": "forced"
    },
    "enrichment_model": "deepseek-v4-flash"
  }
}
